Workbook

Sheet Prima Tarifa
F2: Seguro de Rentas Vitalicias | J2: Calculo de Prima Tarifa
B4: Moneda | C4: Pesos | H4: Caso 1 | K4: Caso 2
B6: Edad Contratación | C6: 65 | D6: =IF(C6>100,"FUERA DE RANGO","") | E6: Valor Anualidad | F6: =Anual!K4+Mensual!M6 -> 20.370346 | H6: ¿Cuánto pagará de prima única? | I6: 1000000 | K6: ¿Cuánto desea recibir de Renta Mensual? | L6: 15000
B8: Plazo del Seguro (w-x) | C8: =Anual!H6 -> 35 | E8: Tasa interes técnico | F8: 0.0947 | H8: Recibirás una Renta Mensual de: | I8: =(I6-(C12+C13+C14)*I6)/(Mensual!M6+0.5*Anual!K4) -> 43287.631 | K8: Recibirás de Renta Anual: | L8: =0.5*L6 -> 7500
E10: Tasa mensual | F10: =12*(((1+F8)^(1/12))-1) -> 0.090822324 | H10: Recibirás una Renta Anual de: | I10: =0.5*I8 -> 21643.815 | K10: Debes pagar de Prima Tarifa | L10: ='Prima Riesgo'!L10/(1-(C12+C13+C14)) -> 346519.31
B12: Gastos Administración | C12: 0.1
B13: Gastos Adquisición | C13: 0.12
B14: Margen Utilidades | C14: 0.08

Sheet Prima Riesgo
F2: Seguro de Rentas Vitalicias | J2: Calculo de Prima Única de Riesgo
B4: Moneda | C4: Pesos | H4: Caso 1 | K4: Caso 2
B6: Edad Contratación | C6: ='Prima Tarifa'!C6 -> 65 | E6: Valor Anualidad | F6: =Anual!K4+Mensual!M6 -> 20.370346 | H6: ¿Cuánto pagará de prima única? | I6: ='Prima Tarifa'!I6 -> 1000000 | K6: ¿Cuánto desea recibir de Renta Mensual? | L6: ='Prima Tarifa'!L6 -> 15000
B8: Plazo del Seguro (w-x) | C8: =Anual!H6 -> 35 | E8: Tasa interes técnico | F8: ='Prima Tarifa'!F8 -> 0.0947 | H8: Recibirás una Renta Mensual de: | I8: =I6/(Mensual!M6+0.5*Anual!K4) -> 61839.472 | K8: Recibirás de Renta Anual: | L8: =0.5*L6 -> 7500
E10: Tasa mensual | F10: =12*(((1+F8)^(1/12))-1) -> 0.090822324 | H10: Recibirás una Renta Anual de: | I10: =0.5*I8 -> 30919.736 | K10: Debes pagar como Prima Única: | L10: =Anual!Q6+Mensual!S8 -> 242563.52

Sheet Mensual
B3: Edad | C3: CNSF 2000-I | D3: qx | E3: lx | F3: dx | G3: px | M3: Seguro de Rentas Vitalicias | Q3: Calculo de de Renta Mensual
B4: 12 | C4: 0.396 | D4: =C4/1000 -> 0.000396 | E4: 1000000 | F4: =D4*E4 -> 396 | G4: =1-D4 -> 0.999604 | I4: Moneda | J4: Pesos
B5: =B4+1/12 -> 12.083333 | D5: =F5/E5 -> 3.3001089e-05 | E5: =E4-(1/12)*F4 -> 999967 | F5: =E5-E6 -> 33 | G5: =1-D5 -> 0.999967
B6: =B5+1/12 -> 12.166667 | D6: =(B6-$B$4)*$D$4 -> 6.6e-05 | E6: =E4-(2/12)*F4 -> 999934 | F6: =E6-E7 -> 33 | G6: =1-D6 -> 0.999934 | I6: Edad Contratación | J6: ='Prima Riesgo'!C6 -> 65 | L6: Valor Anualidad | M6: =T14 -> 11.971456 | O6: ¿Cuánto pagarás de prima única? | P6: ='Prima Riesgo'!I6 -> 1000000 | R6: ¿Cuánto quieres recibir de Renta Mensual? | S6: ='Prima Riesgo'!L6 -> 15000
B7: =B6+1/12 -> 12.25 | D7: =(B7-$B$4)*$D$4 -> 9.9e-05 | E7: =E4-(3/12)*F4 -> 999901 | F7: =E7-E8 -> 33 | G7: =1-D7 -> 0.999901
B8: =B7+1/12 -> 12.333333 | D8: =(B8-$B$4)*$D$4 -> 0.000132 | E8: =E4-(4/12)*F4 -> 999868 | F8: =E8-E9 -> 33 | G8: =1-D8 -> 0.999868 | I8: Plazo del Seguro (w-x) | J8: =B1060-J6 -> 35 | L8: Tasa interes técnico | M8: ='Prima Riesgo'!F8 -> 0.0947 | O8: Recibirás de Renta Mensual: | P8: =P6/T14 -> 83532.025 | R8: Debes pagar como Prima Única: | S8: =S6*T14 -> 179571.85
B9: =B8+1/12 -> 12.416667 | D9: =(B9-$B$4)*$D$4 -> 0.000165 | E9: =E4-(5/12)*F4 -> 999835 | F9: =E9-E10 -> 33 | G9: =1-D9 -> 0.999835
B10: =B9+1/12 -> 12.5 | D10: =(B10-$B$4)*$D$4 -> 0.000198 | E10: =E4-(6/12)*F4 -> 999802 | F10: =E10-E11 -> 33 | G10: =1-D10 -> 0.999802 | L10: Tasa mensual | M10: =12*(((1+M8)^(1/12))-1) -> 0.090822324
B11: =B10+1/12 -> 12.583333 | D11: =(B11-$B$4)*$D$4 -> 0.000231 | E11: =E4-(7/12)*F4 -> 999769 | F11: =E11-E12 -> 33 | G11: =1-D11 -> 0.999769
B12: =B11+1/12 -> 12.666667 | D12: =(B12-$B$4)*$D$4 -> 0.000264 | E12: =E4-(8/12)*F4 -> 999736 | F12: =E12-E13 -> 33 | G12: =1-D12 -> 0.999736
B13: =B12+1/12 -> 12.75 | D13: =(B13-$B$4)*$D$4 -> 0.000297 | E13: =E4-(9/12)*F4 -> 999703 | F13: =E13-E14 -> 33 | G13: =1-D13 -> 0.999703
B14: =B13+1/12 -> 12.833333 | D14: =(B14-$B$4)*$D$4 -> 0.00033 | E14: =E4-(10/12)*F4 -> 999670 | F14: =E14-E15 -> 33 | G14: =1-D14 -> 0.99967 | R14: suma de flujos mensuales | T14: =SUM(T16:T1074) -> 11.971456
B15: =B14+1/12 -> 12.916667 | D15: =(B15-$B$4)*$D$4 -> 0.000363 | E15: =E4-(11/12)*F4 -> 999637 | F15: =E15-E16 -> 33 | G15: =1-D15 -> 0.999637 | I15: t | J15: (x) | K15: qx+t | L15: px | M15: tpx | N15: V^t | Q15: s | R15: spx | S15: V^s | T15: Flujo Anualidad
B16: 13 | C16: 0.427 | D16: =C16/1000 -> 0.000427 | E16: =E4-F4 -> 999604 | F16: =D16*E16 -> 426.83091 | G16: =1-D16 -> 0.999573 | I16: 0 | J16: =J6 -> 65 | K16: =IFERROR(VLOOKUP(J16,$B$3:$F$1060,3,FALSE),"") -> 0.01998 | L16: =IF(I16<>"",1-K16,"") -> 0.98002 | M16: =IF(I16<>"",1,"") -> 1 | N16: =IF(I16<>"",(1+$M$10)^-(1+I16),"") -> 0.91673958 | Q16: 0 | R16: =IF(Q16<>"",1,"") -> 1 | S16: =IF(Q16<>"",(1+$M$10)^-(12*Q16),"") -> 1 | T16: =IFERROR(S16,"") -> 1
B17: =B16+1/12 -> 13.083333 | D17: =F17/E17 -> 3.55846e-05 | E17: =E16-(1/12)*F16 -> 999568.43 | F17: =E17-E18 -> 35.569242 | G17: =1-D17 -> 0.99996442 | I17: =IFERROR(IF(I16+1/12<$J$8,I16+1/12,""),"") -> 0.083333333 | J17: =IF(I17<>"",J16+1/12,"") -> 65.083333 | K17: =IFERROR(VLOOKUP(J17,$B$3:$F$1060,3,FALSE),"") -> 0.001665 | L17: =IF(I17<>"",1-K17,"") -> 0.998335 | M17: =IF(I17<>"",M16*L16,"") -> 0.98002 | N17: =IF(I17<>"",(1+$M$10)^-(1+I17),"") -> 0.91012242 | P17: M | Q17: =IFERROR(IF(Q16+1/12<$J$8,Q16+1/12,""),"") -> 0.083333333 | R17: =IF(Q17<>"",R16*L16,"") -> 0.98002 | S17: =IF(Q17<>"",(1+$M$10)^-(12*Q17),"") -> 0.91673958 | T17: =IFERROR(S17,"") -> 0.91673958
B18: =B17+1/12 -> 13.166667 | D18: =(B18-$B$16)*$D$16 -> 7.1166667e-05 | E18: =E16-(2/12)*F16 -> 999532.86 | F18: =E18-E19 -> 35.569242 | G18: =1-D18 -> 0.99992883 | I18: =IFERROR(IF(I17+1/12<$J$8,I17+1/12,""),"") -> 0.16666667 | J18: =IF(I18<>"",J17+1/12,"") -> 65.166667 | K18: =IFERROR(VLOOKUP(J18,$B$3:$F$1060,3,FALSE),"") -> 0.00333 | L18: =IF(I18<>"",1-K18,"") -> 0.99667 | M18: =IF(I18<>"",M17*L17,"") -> 0.97838827 | N18: =IF(I18<>"",(1+$M$10)^-(1+I18),"") -> 0.90355303 | P18: E | Q18: =IFERROR(IF(Q17+1/12<$J$8,Q17+1/12,""),"") -> 0.16666667 | R18: =IF(Q18<>"",R17*L17,"") -> 0.97838827 | S18: =IF(Q18<>"",(1+$M$10)^-(12*Q18),"") -> 0.84041146 | T18: =IFERROR(S18,"") -> 0.84041146
B19: =B18+1/12 -> 13.25 | D19: =(B19-$B$16)*$D$16 -> 0.00010675 | E19: =E16-(3/12)*F16 -> 999497.29 | F19: =E19-E20 -> 35.569242 | G19: =1-D19 -> 0.99989325 | I19: =IFERROR(IF(I18+1/12<$J$8,I18+1/12,""),"") -> 0.25 | J19: =IF(I19<>"",J18+1/12,"") -> 65.25 | K19: =IFERROR(VLOOKUP(J19,$B$3:$F$1060,3,FALSE),"") -> 0.004995 | L19: =IF(I19<>"",1-K19,"") -> 0.995005 | M19: =IF(I19<>"",M18*L18,"") -> 0.97513023 | N19: =IF(I19<>"",(1+$M$10)^-(1+I19),"") -> 0.89703105 | P19: N | Q19: =IFERROR(IF(Q18+1/12<$J$8,Q18+1/12,""),"") -> 0.25 | R19: =IF(Q19<>"",R18*L18,"") -> 0.97513023 | S19: =IF(Q19<>"",(1+$M$10)^-(12*Q19),"") -> 0.77043845 | T19: =IFERROR(S19,"") -> 0.77043845
B20: =B19+1/12 -> 13.333333 | D20: =(B20-$B$16)*$D$16 -> 0.00014233333 | E20: =E16-(4/12)*F16 -> 999461.72 | F20: =E20-E21 -> 35.569242 | G20: =1-D20 -> 0.99985767 | I20: =IFERROR(IF(I19+1/12<$J$8,I19+1/12,""),"") -> 0.33333333 | J20: =IF(I20<>"",J19+1/12,"") -> 65.333333 | K20: =IFERROR(VLOOKUP(J20,$B$3:$F$1060,3,FALSE),"") -> 0.00666 | L20: =IF(I20<>"",1-K20,"") -> 0.99334 | M20: =IF(I20<>"",M19*L19,"") -> 0.97025946 | N20: =IF(I20<>"",(1+$M$10)^-(1+I20),"") -> 0.89055616 | P20: S | Q20: =IFERROR(IF(Q19+1/12<$J$8,Q19+1/12,""),"") -> 0.33333333 | R20: =IF(Q20<>"",R19*L19,"") -> 0.97025946 | S20: =IF(Q20<>"",(1+$M$10)^-(12*Q20),"") -> 0.70629142 | T20: =IFERROR(S20,"") -> 0.70629142
B21: =B20+1/12 -> 13.416667 | D21: =(B21-$B$16)*$D$16 -> 0.00017791667 | E21: =E16-(5/12)*F16 -> 999426.15 | F21: =E21-E22 -> 35.569242 | G21: =1-D21 -> 0.99982208 | I21: =IFERROR(IF(I20+1/12<$J$8,I20+1/12,""),"") -> 0.41666667 | J21: =IF(I21<>"",J20+1/12,"") -> 65.416667 | K21: =IFERROR(VLOOKUP(J21,$B$3:$F$1060,3,FALSE),"") -> 0.008325 | L21: =IF(I21<>"",1-K21,"") -> 0.991675 | M21: =IF(I21<>"",M20*L20,"") -> 0.96379753 | N21: =IF(I21<>"",(1+$M$10)^-(1+I21),"") -> 0.88412799 | P21: U | Q21: =IFERROR(IF(Q20+1/12<$J$8,Q20+1/12,""),"") -> 0.41666667 | R21: =IF(Q21<>"",R20*L20,"") -> 0.96379753 | S21: =IF(Q21<>"",(1+$M$10)^-(12*Q21),"") -> 0.6474853 | T21: =IFERROR(S21,"") -> 0.6474853
B22: =B21+1/12 -> 13.5 | D22: =(B22-$B$16)*$D$16 -> 0.0002135 | E22: =E16-(6/12)*F16 -> 999390.58 | F22: =E22-E23 -> 35.569242 | G22: =1-D22 -> 0.9997865 | I22: =IFERROR(IF(I21+1/12<$J$8,I21+1/12,""),"") -> 0.5 | J22: =IF(I22<>"",J21+1/12,"") -> 65.5 | K22: =IFERROR(VLOOKUP(J22,$B$3:$F$1060,3,FALSE),"") -> 0.00999 | L22: =IF(I22<>"",1-K22,"") -> 0.99001 | M22: =IF(I22<>"",M21*L21,"") -> 0.95577392 | N22: =IF(I22<>"",(1+$M$10)^-(1+I22),"") -> 0.87774623 | P22: A | Q22: =IFERROR(IF(Q21+1/12<$J$8,Q21+1/12,""),"") -> 0.5 | R22: =IF(Q22<>"",R21*L21,"") -> 0.95577392 | S22: =IF(Q22<>"",(1+$M$10)^-(12*Q22),"") -> 0.5935754 | T22: =IFERROR(S22,"") -> 0.5935754
B23: =B22+1/12 -> 13.583333 | D23: =(B23-$B$16)*$D$16 -> 0.00024908333 | E23: =E16-(7/12)*F16 -> 999355.02 | F23: =E23-E24 -> 35.569242 | G23: =1-D23 -> 0.99975092 | I23: =IFERROR(IF(I22+1/12<$J$8,I22+1/12,""),"") -> 0.58333333 | J23: =IF(I23<>"",J22+1/12,"") -> 65.583333 | K23: =IFERROR(VLOOKUP(J23,$B$3:$F$1060,3,FALSE),"") -> 0.011655 | L23: =IF(I23<>"",1-K23,"") -> 0.988345 | M23: =IF(I23<>"",M22*L22,"") -> 0.94622573 | N23: =IF(I23<>"",(1+$M$10)^-(1+I23),"") -> 0.87141053 | P23: L | Q23: =IFERROR(IF(Q22+1/12<$J$8,Q22+1/12,""),"") -> 0.58333333 | R23: =IF(Q23<>"",R22*L22,"") -> 0.94622573 | S23: =IF(Q23<>"",(1+$M$10)^-(12*Q23),"") -> 0.54415406 | T23: =IFERROR(S23,"") -> 0.54415406
B24: =B23+1/12 -> 13.666667 | D24: =(B24-$B$16)*$D$16 -> 0.00028466667 | E24: =E16-(8/12)*F16 -> 999319.45 | F24: =E24-E25 -> 35.569242 | G24: =1-D24 -> 0.99971533 | I24: =IFERROR(IF(I23+1/12<$J$8,I23+1/12,""),"") -> 0.66666667 | J24: =IF(I24<>"",J23+1/12,"") -> 65.666667 | K24: =IFERROR(VLOOKUP(J24,$B$3:$F$1060,3,FALSE),"") -> 0.01332 | L24: =IF(I24<>"",1-K24,"") -> 0.98668 | M24: =IF(I24<>"",M23*L23,"") -> 0.93519747 | N24: =IF(I24<>"",(1+$M$10)^-(1+I24),"") -> 0.86512057 | P24: I | Q24: =IFERROR(IF(Q23+1/12<$J$8,Q23+1/12,""),"") -> 0.66666667 | R24: =IF(Q24<>"",R23*L23,"") -> 0.93519747 | S24: =IF(Q24<>"",(1+$M$10)^-(12*Q24),"") -> 0.49884757 | T24: =IFERROR(S24,"") -> 0.49884757
B25: =B24+1/12 -> 13.75 | D25: =(B25-$B$16)*$D$16 -> 0.00032025 | E25: =E16-(9/12)*F16 -> 999283.88 | F25: =E25-E26 -> 35.569242 | G25: =1-D25 -> 0.99967975 | I25: =IFERROR(IF(I24+1/12<$J$8,I24+1/12,""),"") -> 0.75 | J25: =IF(I25<>"",J24+1/12,"") -> 65.75 | K25: =IFERROR(VLOOKUP(J25,$B$3:$F$1060,3,FALSE),"") -> 0.014985 | L25: =IF(I25<>"",1-K25,"") -> 0.985015 | M25: =IF(I25<>"",M24*L24,"") -> 0.92274064 | N25: =IF(I25<>"",(1+$M$10)^-(1+I25),"") -> 0.858876 | P25: D | Q25: =IFERROR(IF(Q24+1/12<$J$8,Q24+1/12,""),"") -> 0.75 | R25: =IF(Q25<>"",R24*L24,"") -> 0.92274064 | S25: =IF(Q25<>"",(1+$M$10)^-(12*Q25),"") -> 0.45731331 | T25: =IFERROR(S25,"") -> 0.45731331
B26: =B25+1/12 -> 13.833333 | D26: =(B26-$B$16)*$D$16 -> 0.00035583333 | E26: =E16-(10/12)*F16 -> 999248.31 | F26: =E26-E27 -> 35.569242 | G26: =1-D26 -> 0.99964417 | I26: =IFERROR(IF(I25+1/12<$J$8,I25+1/12,""),"") -> 0.83333333 | J26: =IF(I26<>"",J25+1/12,"") -> 65.833333 | K26: =IFERROR(VLOOKUP(J26,$B$3:$F$1060,3,FALSE),"") -> 0.01665 | L26: =IF(I26<>"",1-K26,"") -> 0.98335 | M26: =IF(I26<>"",M25*L25,"") -> 0.90891337 | N26: =IF(I26<>"",(1+$M$10)^-(1+I26),"") -> 0.85267651 | P26: A | Q26: =IFERROR(IF(Q25+1/12<$J$8,Q25+1/12,""),"") -> 0.83333333 | R26: =IF(Q26<>"",R25*L25,"") -> 0.90891337 | S26: =IF(Q26<>"",(1+$M$10)^-(12*Q26),"") -> 0.41923721 | T26: =IFERROR(S26,"") -> 0.41923721
B27: =B26+1/12 -> 13.916667 | D27: =(B27-$B$16)*$D$16 -> 0.00039141667 | E27: =E16-(11/12)*F16 -> 999212.74 | F27: =E27-E28 -> 35.569242 | G27: =1-D27 -> 0.99960858 | I27: =IFERROR(IF(I26+1/12<$J$8,I26+1/12,""),"") -> 0.91666667 | J27: =IF(I27<>"",J26+1/12,"") -> 65.916667 | K27: =IFERROR(VLOOKUP(J27,$B$3:$F$1060,3,FALSE),"") -> 0.018315 | L27: =IF(I27<>"",1-K27,"") -> 0.981685 | M27: =IF(I27<>"",M26*L26,"") -> 0.89377997 | N27: =IF(I27<>"",(1+$M$10)^-(1+I27),"") -> 0.84652177 | P27: D | Q27: =IFERROR(IF(Q26+1/12<$J$8,Q26+1/12,""),"") -> 0.91666667 | R27: =IF(Q27<>"",R26*L26,"") -> 0.89377997 | S27: =IF(Q27<>"",(1+$M$10)^-(12*Q27),"") -> 0.38433135 | T27: =IFERROR(S27,"") -> 0.38433135
B28: 14 | C28: 0.46 | D28: =C28/1000 -> 0.00046 | E28: =E16-F16 -> 999177.17 | F28: =D28*E28 -> 459.6215 | G28: =1-D28 -> 0.99954 | I28: =IFERROR(IF(I27+1/12<$J$8,I27+1/12,""),"") -> 1 | J28: =IF(I28<>"",J27+1/12,"") -> 66 | K28: =IFERROR(VLOOKUP(J28,$B$3:$F$1060,3,TRUE),"") -> 0.018315 | L28: =IF(I28<>"",1-K28,"") -> 0.981685 | M28: =IF(I28<>"",M27*L27,"") -> 0.87741039 | N28: =IF(I28<>"",(1+$M$10)^-(1+I28),"") -> 0.84041146 | P28: E | Q28: =IFERROR(IF(Q27+1/12<$J$8,Q27+1/12,""),"") -> 1 | R28: =IF(Q28<>"",R27*L27,"") -> 0.87741039 | S28: =IF(Q28<>"",(1+$M$10)^-(12*Q28),"") -> 0.35233176 | T28: =IFERROR(S28,"") -> 0.35233176
B29: =B28+1/12 -> 14.083333 | D29: =(B29-$B$28)*$D$28 -> 3.8333333e-05 | E29: =E28-(1/12)*F28 -> 999138.87 | F29: =E29-E30 -> 38.301791 | G29: =1-D29 -> 0.99996167 | I29: =IFERROR(IF(I28+1/12<$J$8,I28+1/12,""),"") -> 1.0833333 | J29: =IF(I29<>"",J28+1/12,"") -> 66.083333 | K29: =IFERROR(VLOOKUP(J29,$B$3:$F$1060,3,TRUE),"") -> 0.02149 | L29: =IF(I29<>"",1-K29,"") -> 0.97851 | M29: =IF(I29<>"",M28*L28,"") -> 0.86134062 | N29: =IF(I29<>"",(1+$M$10)^-(1+I29),"") -> 0.83434525 | P29: S | Q29: =IFERROR(IF(Q28+1/12<$J$8,Q28+1/12,""),"") -> 1.0833333 | R29: =IF(Q29<>"",R28*L28,"") -> 0.86134062 | S29: =IF(Q29<>"",(1+$M$10)^-(12*Q29),"") -> 0.32299647 | T29: =IFERROR(S29,"") -> 0.32299647
B30: =B29+1/12 -> 14.166667 | D30: =(B30-$B$28)*$D$28 -> 7.6666667e-05 | E30: =E28-(2/12)*F28 -> 999100.57 | F30: =E30-E31 -> 38.301791 | G30: =1-D30 -> 0.99992333 | I30: =IFERROR(IF(I29+1/12<$J$8,I29+1/12,""),"") -> 1.1666667 | J30: =IF(I30<>"",J29+1/12,"") -> 66.166667 | K30: =IFERROR(VLOOKUP(J30,$B$3:$F$1060,3,TRUE),"") -> 0.0017908333 | L30: =IF(I30<>"",1-K30,"") -> 0.99820917 | M30: =IF(I30<>"",M29*L29,"") -> 0.84283041 | N30: =IF(I30<>"",(1+$M$10)^-(1+I30),"") -> 0.82832283 | Q30: =IFERROR(IF(Q29+1/12<$J$8,Q29+1/12,""),"") -> 1.1666667 | R30: =IF(Q30<>"",R29*L29,"") -> 0.84283041 | S30: =IF(Q30<>"",(1+$M$10)^-(12*Q30),"") -> 0.29610365 | T30: =IFERROR(S30,"") -> 0.29610365
B31: =B30+1/12 -> 14.25 | D31: =(B31-$B$28)*$D$28 -> 0.000115 | E31: =E28-(3/12)*F28 -> 999062.26 | F31: =E31-E32 -> 38.301791 | G31: =1-D31 -> 0.999885 | I31: =IFERROR(IF(I30+1/12<$J$8,I30+1/12,""),"") -> 1.25 | J31: =IF(I31<>"",J30+1/12,"") -> 66.25 | K31: =IFERROR(VLOOKUP(J31,$B$3:$F$1060,3,TRUE),"") -> 0.0035816667 | L31: =IF(I31<>"",1-K31,"") -> 0.99641833 | M31: =IF(I31<>"",M30*L30,"") -> 0.84132104 | N31: =IF(I31<>"",(1+$M$10)^-(1+I31),"") -> 0.82234387 | P31: G | Q31: =IFERROR(IF(Q30+1/12<$J$8,Q30+1/12,""),"") -> 1.25 | R31: =IF(Q31<>"",R30*L30,"") -> 0.84132104 | S31: =IF(Q31<>"",(1+$M$10)^-(12*Q31),"") -> 0.27144993 | T31: =IFERROR(S31,"") -> 0.27144993
B32: =B31+1/12 -> 14.333333 | D32: =(B32-$B$28)*$D$28 -> 0.00015333333 | E32: =E28-(4/12)*F28 -> 999023.96 | F32: =E32-E33 -> 38.301791 | G32: =1-D32 -> 0.99984667 | I32: =IFERROR(IF(I31+1/12<$J$8,I31+1/12,""),"") -> 1.3333333 | J32: =IF(I32<>"",J31+1/12,"") -> 66.333333 | K32: =IFERROR(VLOOKUP(J32,$B$3:$F$1060,3,TRUE),"") -> 0.0053725 | L32: =IF(I32<>"",1-K32,"") -> 0.9946275 | M32: =IF(I32<>"",M31*L31,"") -> 0.83830771 | N32: =IF(I32<>"",(1+$M$10)^-(1+I32),"") -> 0.81640808 | P32: A | Q32: =IFERROR(IF(Q31+1/12<$J$8,Q31+1/12,""),"") -> 1.3333333 | R32: =IF(Q32<>"",R31*L31,"") -> 0.83830771 | S32: =IF(Q32<>"",(1+$M$10)^-(12*Q32),"") -> 0.2488489 | T32: =IFERROR(S32,"") -> 0.2488489
B33: =B32+1/12 -> 14.416667 | D33: =(B33-$B$28)*$D$28 -> 0.00019166667 | E33: =E28-(5/12)*F28 -> 998985.66 | F33: =E33-E34 -> 38.301791 | G33: =1-D33 -> 0.99980833 | I33: =IFERROR(IF(I32+1/12<$J$8,I32+1/12,""),"") -> 1.4166667 | J33: =IF(I33<>"",J32+1/12,"") -> 66.416667 | K33: =IFERROR(VLOOKUP(J33,$B$3:$F$1060,3,TRUE),"") -> 0.0071633333 | L33: =IF(I33<>"",1-K33,"") -> 0.99283667 | M33: =IF(I33<>"",M32*L32,"") -> 0.8338039 | N33: =IF(I33<>"",(1+$M$10)^-(1+I33),"") -> 0.81051513 | P33: R | Q33: =IFERROR(IF(Q32+1/12<$J$8,Q32+1/12,""),"") -> 1.4166667 | R33: =IF(Q33<>"",R32*L32,"") -> 0.8338039 | S33: =IF(Q33<>"",(1+$M$10)^-(12*Q33),"") -> 0.22812963 | T33: =IFERROR(S33,"") -> 0.22812963
B34: =B33+1/12 -> 14.5 | D34: =(B34-$B$28)*$D$28 -> 0.00023 | E34: =E28-(6/12)*F28 -> 998947.36 | F34: =E34-E35 -> 38.301791 | G34: =1-D34 -> 0.99977 | I34: =IFERROR(IF(I33+1/12<$J$8,I33+1/12,""),"") -> 1.5 | J34: =IF(I34<>"",J33+1/12,"") -> 66.5 | K34: =IFERROR(VLOOKUP(J34,$B$3:$F$1060,3,TRUE),"") -> 0.0089541667 | L34: =IF(I34<>"",1-K34,"") -> 0.99104583 | M34: =IF(I34<>"",M33*L33,"") -> 0.82783108 | N34: =IF(I34<>"",(1+$M$10)^-(1+I34),"") -> 0.80466471 | P34: A | Q34: =IFERROR(IF(Q33+1/12<$J$8,Q33+1/12,""),"") -> 1.5 | R34: =IF(Q34<>"",R33*L33,"") -> 0.82783108 | S34: =IF(Q34<>"",(1+$M$10)^-(12*Q34),"") -> 0.20913546 | T34: =IFERROR(S34,"") -> 0.20913546
B35: =B34+1/12 -> 14.583333 | D35: =(B35-$B$28)*$D$28 -> 0.00026833333 | E35: =E28-(7/12)*F28 -> 998909.06 | F35: =E35-E36 -> 38.301791 | G35: =1-D35 -> 0.99973167 | I35: =IFERROR(IF(I34+1/12<$J$8,I34+1/12,""),"") -> 1.5833333 | J35: =IF(I35<>"",J34+1/12,"") -> 66.583333 | K35: =IFERROR(VLOOKUP(J35,$B$3:$F$1060,3,TRUE),"") -> 0.010745 | L35: =IF(I35<>"",1-K35,"") -> 0.989255 | M35: =IF(I35<>"",M34*L34,"") -> 0.82041854 | N35: =IF(I35<>"",(1+$M$10)^-(1+I35),"") -> 0.79885653 | P35: N | Q35: =IFERROR(IF(Q34+1/12<$J$8,Q34+1/12,""),"") -> 1.5833333 | R35: =IF(Q35<>"",R34*L34,"") -> 0.82041854 | S35: =IF(Q35<>"",(1+$M$10)^-(12*Q35),"") -> 0.19172276 | T35: =IFERROR(S35,"") -> 0.19172276
B36: =B35+1/12 -> 14.666667 | D36: =(B36-$B$28)*$D$28 -> 0.00030666667 | E36: =E28-(8/12)*F28 -> 998870.75 | F36: =E36-E37 -> 38.301791 | G36: =1-D36 -> 0.99969333 | I36: =IFERROR(IF(I35+1/12<$J$8,I35+1/12,""),"") -> 1.6666667 | J36: =IF(I36<>"",J35+1/12,"") -> 66.666667 | K36: =IFERROR(VLOOKUP(J36,$B$3:$F$1060,3,TRUE),"") -> 0.012535833 | L36: =IF(I36<>"",1-K36,"") -> 0.98746417 | M36: =IF(I36<>"",M35*L35,"") -> 0.81160315 | N36: =IF(I36<>"",(1+$M$10)^-(1+I36),"") -> 0.79309027 | P36: T | Q36: =IFERROR(IF(Q35+1/12<$J$8,Q35+1/12,""),"") -> 1.6666667 | R36: =IF(Q36<>"",R35*L35,"") -> 0.81160315 | S36: =IF(Q36<>"",(1+$M$10)^-(12*Q36),"") -> 0.17575984 | T36: =IFERROR(S36,"") -> 0.17575984
B37: =B36+1/12 -> 14.75 | D37: =(B37-$B$28)*$D$28 -> 0.000345 | E37: =E28-(9/12)*F28 -> 998832.45 | F37: =E37-E38 -> 38.301791 | G37: =1-D37 -> 0.999655 | I37: =IFERROR(IF(I36+1/12<$J$8,I36+1/12,""),"") -> 1.75 | J37: =IF(I37<>"",J36+1/12,"") -> 66.75 | K37: =IFERROR(VLOOKUP(J37,$B$3:$F$1060,3,TRUE),"") -> 0.014326667 | L37: =IF(I37<>"",1-K37,"") -> 0.98567333 | M37: =IF(I37<>"",M36*L36,"") -> 0.80142903 | N37: =IF(I37<>"",(1+$M$10)^-(1+I37),"") -> 0.78736563 | P37: I | Q37: =IFERROR(IF(Q36+1/12<$J$8,Q36+1/12,""),"") -> 1.75 | R37: =IF(Q37<>"",R36*L36,"") -> 0.80142903 | S37: =IF(Q37<>"",(1+$M$10)^-(12*Q37),"") -> 0.161126 | T37: =IFERROR(S37,"") -> 0.161126
B38: =B37+1/12 -> 14.833333 | D38: =(B38-$B$28)*$D$28 -> 0.00038333333 | E38: =E28-(10/12)*F28 -> 998794.15 | F38: =E38-E39 -> 38.301791 | G38: =1-D38 -> 0.99961667 | I38: =IFERROR(IF(I37+1/12<$J$8,I37+1/12,""),"") -> 1.8333333 | J38: =IF(I38<>"",J37+1/12,"") -> 66.833333 | K38: =IFERROR(VLOOKUP(J38,$B$3:$F$1060,3,TRUE),"") -> 0.0161175 | L38: =IF(I38<>"",1-K38,"") -> 0.9838825 | M38: =IF(I38<>"",M37*L37,"") -> 0.78994722 | N38: =IF(I38<>"",(1+$M$10)^-(1+I38),"") -> 0.78168231 | P38: Z | Q38: =IFERROR(IF(Q37+1/12<$J$8,Q37+1/12,""),"") -> 1.8333333 | R38: =IF(Q38<>"",R37*L37,"") -> 0.78994722 | S38: =IF(Q38<>"",(1+$M$10)^-(12*Q38),"") -> 0.14771058 | T38: =IFERROR(S38,"") -> 0.14771058
B39: =B38+1/12 -> 14.916667 | D39: =(B39-$B$28)*$D$28 -> 0.00042166667 | E39: =E28-(11/12)*F28 -> 998755.85 | F39: =E39-E40 -> 38.301791 | G39: =1-D39 -> 0.99957833 | I39: =IFERROR(IF(I38+1/12<$J$8,I38+1/12,""),"") -> 1.9166667 | J39: =IF(I39<>"",J38+1/12,"") -> 66.916667 | K39: =IFERROR(VLOOKUP(J39,$B$3:$F$1060,3,TRUE),"") -> 0.017908333 | L39: =IF(I39<>"",1-K39,"") -> 0.98209167 | M39: =IF(I39<>"",M38*L38,"") -> 0.77721524 | N39: =IF(I39<>"",(1+$M$10)^-(1+I39),"") -> 0.77604002 | P39: A | Q39: =IFERROR(IF(Q38+1/12<$J$8,Q38+1/12,""),"") -> 1.9166667 | R39: =IF(Q39<>"",R38*L38,"") -> 0.77721524 | S39: =IF(Q39<>"",(1+$M$10)^-(12*Q39),"") -> 0.13541214 | T39: =IFERROR(S39,"") -> 0.13541214
B40: 15 | C40: 0.495 | D40: =C40/1000 -> 0.000495 | E40: =E28-F28 -> 998717.55 | F40: =D40*E40 -> 494.36519 | G40: =1-D40 -> 0.999505 | I40: =IFERROR(IF(I39+1/12<$J$8,I39+1/12,""),"") -> 2 | J40: =IF(I40<>"",J39+1/12,"") -> 67 | K40: =IFERROR(VLOOKUP(J40,$B$3:$F$1060,3,TRUE),"") -> 0.019699167 | L40: =IF(I40<>"",1-K40,"") -> 0.98030083 | M40: =IF(I40<>"",M39*L39,"") -> 0.76329662 | N40: =IF(I40<>"",(1+$M$10)^-(1+I40),"") -> 0.77043845 | P40: D | Q40: =IFERROR(IF(Q39+1/12<$J$8,Q39+1/12,""),"") -> 2 | R40: =IF(Q40<>"",R39*L39,"") -> 0.76329662 | S40: =IF(Q40<>"",(1+$M$10)^-(12*Q40),"") -> 0.12413767 | T40: =IFERROR(S40,"") -> 0.12413767
B41: =B40+1/12 -> 15.083333 | D41: =(B41-$B$40)*$D$40 -> 4.125e-05 | E41: =E40-(1/12)*F40 -> 998676.35 | F41: =E41-E42 -> 41.197099 | G41: =1-D41 -> 0.99995875 | I41: =IFERROR(IF(I40+1/12<$J$8,I40+1/12,""),"") -> 2.0833333 | J41: =IF(I41<>"",J40+1/12,"") -> 67.083333 | K41: =IFERROR(VLOOKUP(J41,$B$3:$F$1060,3,TRUE),"") -> 0.023111 | L41: =IF(I41<>"",1-K41,"") -> 0.976889 | M41: =IF(I41<>"",M40*L40,"") -> 0.74826031 | N41: =IF(I41<>"",(1+$M$10)^-(1+I41),"") -> 0.76487731 | P41: A | Q41: =IFERROR(IF(Q40+1/12<$J$8,Q40+1/12,""),"") -> 2.0833333 | R41: =IF(Q41<>"",R40*L40,"") -> 0.74826031 | S41: =IF(Q41<>"",(1+$M$10)^-(12*Q41),"") -> 0.11380191 | T41: =IFERROR(S41,"") -> 0.11380191
B42: =B41+1/12 -> 15.166667 | D42: =(B42-$B$40)*$D$40 -> 8.25e-05 | E42: =E40-(2/12)*F40 -> 998635.15 | F42: =E42-E43 -> 41.197099 | G42: =1-D42 -> 0.9999175 | I42: =IFERROR(IF(I41+1/12<$J$8,I41+1/12,""),"") -> 2.1666667 | J42: =IF(I42<>"",J41+1/12,"") -> 67.166667 | K42: =IFERROR(VLOOKUP(J42,$B$3:$F$1060,3,TRUE),"") -> 0.0019259167 | L42: =IF(I42<>"",1-K42,"") -> 0.99807408 | M42: =IF(I42<>"",M41*L41,"") -> 0.73096726 | N42: =IF(I42<>"",(1+$M$10)^-(1+I42),"") -> 0.75935632 | P42: S | Q42: =IFERROR(IF(Q41+1/12<$J$8,Q41+1/12,""),"") -> 2.1666667 | R42: =IF(Q42<>"",R41*L41,"") -> 0.73096726 | S42: =IF(Q42<>"",(1+$M$10)^-(12*Q42),"") -> 0.10432672 | T42: =IFERROR(S42,"") -> 0.10432672
B43: =B42+1/12 -> 15.25 | D43: =(B43-$B$40)*$D$40 -> 0.00012375 | E43: =E40-(3/12)*F40 -> 998593.96 | F43: =E43-E44 -> 41.197099 | G43: =1-D43 -> 0.99987625 | I43: =IFERROR(IF(I42+1/12<$J$8,I42+1/12,""),"") -> 2.25 | J43: =IF(I43<>"",J42+1/12,"") -> 67.25 | K43: =IFERROR(VLOOKUP(J43,$B$3:$F$1060,3,TRUE),"") -> 0.0038518333 | L43: =IF(I43<>"",1-K43,"") -> 0.99614817 | M43: =IF(I43<>"",M42*L42,"") -> 0.72955948 | N43: =IF(I43<>"",(1+$M$10)^-(1+I43),"") -> 0.75387518 | Q43: =IFERROR(IF(Q42+1/12<$J$8,Q42+1/12,""),"") -> 2.25 | R43: =IF(Q43<>"",R42*L42,"") -> 0.72955948 | S43: =IF(Q43<>"",(1+$M$10)^-(12*Q43),"") -> 0.095640432 | T43: =IFERROR(S43,"") -> 0.095640432
B44: =B43+1/12 -> 15.333333 | D44: =(B44-$B$40)*$D$40 -> 0.000165 | E44: =E40-(4/12)*F40 -> 998552.76 | F44: =E44-E45 -> 41.197099 | G44: =1-D44 -> 0.999835 | I44: =IFERROR(IF(I43+1/12<$J$8,I43+1/12,""),"") -> 2.3333333 | J44: =IF(I44<>"",J43+1/12,"") -> 67.333333 | K44: =IFERROR(VLOOKUP(J44,$B$3:$F$1060,3,TRUE),"") -> 0.00577775 | L44: =IF(I44<>"",1-K44,"") -> 0.99422225 | M44: =IF(I44<>"",M43*L43,"") -> 0.72674934 | N44: =IF(I44<>"",(1+$M$10)^-(1+I44),"") -> 0.7484336 | Q44: =IFERROR(IF(Q43+1/12<$J$8,Q43+1/12,""),"") -> 2.3333333 | R44: =IF(Q44<>"",R43*L43,"") -> 0.72674934 | S44: =IF(Q44<>"",(1+$M$10)^-(12*Q44),"") -> 0.087677369 | T44: =IFERROR(S44,"") -> 0.087677369
B45: =B44+1/12 -> 15.416667 | D45: =(B45-$B$40)*$D$40 -> 0.00020625 | E45: =E40-(5/12)*F40 -> 998511.56 | F45: =E45-E46 -> 41.197099 | G45: =1-D45 -> 0.99979375 | I45: =IFERROR(IF(I44+1/12<$J$8,I44+1/12,""),"") -> 2.4166667 | J45: =IF(I45<>"",J44+1/12,"") -> 67.416667 | K45: =IFERROR(VLOOKUP(J45,$B$3:$F$1060,3,TRUE),"") -> 0.0077036667 | L45: =IF(I45<>"",1-K45,"") -> 0.99229633 | M45: =IF(I45<>"",M44*L44,"") -> 0.72255036 | N45: =IF(I45<>"",(1+$M$10)^-(1+I45),"") -> 0.7430313 | Q45: =IFERROR(IF(Q44+1/12<$J$8,Q44+1/12,""),"") -> 2.4166667 | R45: =IF(Q45<>"",R44*L44,"") -> 0.72255036 | S45: =IF(Q45<>"",(1+$M$10)^-(12*Q45),"") -> 0.080377315 | T45: =IFERROR(S45,"") -> 0.080377315
B46: =B45+1/12 -> 15.5 | D46: =(B46-$B$40)*$D$40 -> 0.0002475 | E46: =E40-(6/12)*F40 -> 998470.37 | F46: =E46-E47 -> 41.197099 | G46: =1-D46 -> 0.9997525 | I46: =IFERROR(IF(I45+1/12<$J$8,I45+1/12,""),"") -> 2.5 | J46: =IF(I46<>"",J45+1/12,"") -> 67.5 | K46: =IFERROR(VLOOKUP(J46,$B$3:$F$1060,3,TRUE),"") -> 0.0096295833 | L46: =IF(I46<>"",1-K46,"") -> 0.99037042 | M46: =IF(I46<>"",M45*L45,"") -> 0.71698408 | N46: =IF(I46<>"",(1+$M$10)^-(1+I46),"") -> 0.73766799 | Q46: =IFERROR(IF(Q45+1/12<$J$8,Q45+1/12,""),"") -> 2.5 | R46: =IF(Q46<>"",R45*L45,"") -> 0.71698408 | S46: =IF(Q46<>"",(1+$M$10)^-(12*Q46),"") -> 0.073685066 | T46: =IFERROR(S46,"") -> 0.073685066
B47: =B46+1/12 -> 15.583333 | D47: =(B47-$B$40)*$D$40 -> 0.00028875 | E47: =E40-(7/12)*F40 -> 998429.17 | F47: =E47-E48 -> 41.197099 | G47: =1-D47 -> 0.99971125 | I47: =IFERROR(IF(I46+1/12<$J$8,I46+1/12,""),"") -> 2.5833333 | J47: =IF(I47<>"",J46+1/12,"") -> 67.583333 | K47: =IFERROR(VLOOKUP(J47,$B$3:$F$1060,3,TRUE),"") -> 0.0115555 | L47: =IF(I47<>"",1-K47,"") -> 0.9884445 | M47: =IF(I47<>"",M46*L46,"") -> 0.71007982 | N47: =IF(I47<>"",(1+$M$10)^-(1+I47),"") -> 0.7323434 | Q47: =IFERROR(IF(Q46+1/12<$J$8,Q46+1/12,""),"") -> 2.5833333 | R47: =IF(Q47<>"",R46*L46,"") -> 0.71007982 | S47: =IF(Q47<>"",(1+$M$10)^-(12*Q47),"") -> 0.067550016 | T47: =IFERROR(S47,"") -> 0.067550016
B48: =B47+1/12 -> 15.666667 | D48: =(B48-$B$40)*$D$40 -> 0.00033 | E48: =E40-(8/12)*F40 -> 998387.97 | F48: =E48-E49 -> 41.197099 | G48: =1-D48 -> 0.99967 | I48: =IFERROR(IF(I47+1/12<$J$8,I47+1/12,""),"") -> 2.6666667 | J48: =IF(I48<>"",J47+1/12,"") -> 67.666667 | K48: =IFERROR(VLOOKUP(J48,$B$3:$F$1060,3,TRUE),"") -> 0.013481417 | L48: =IF(I48<>"",1-K48,"") -> 0.98651858 | M48: =IF(I48<>"",M47*L47,"") -> 0.70187449 | N48: =IF(I48<>"",(1+$M$10)^-(1+I48),"") -> 0.72705724 | Q48: =IFERROR(IF(Q47+1/12<$J$8,Q47+1/12,""),"") -> 2.6666667 | R48: =IF(Q48<>"",R47*L47,"") -> 0.70187449 | S48: =IF(Q48<>"",(1+$M$10)^-(12*Q48),"") -> 0.061925774 | T48: =IFERROR(S48,"") -> 0.061925774
B49: =B48+1/12 -> 15.75 | D49: =(B49-$B$40)*$D$40 -> 0.00037125 | E49: =E40-(9/12)*F40 -> 998346.77 | F49: =E49-E50 -> 41.197099 | G49: =1-D49 -> 0.99962875 | I49: =IFERROR(IF(I48+1/12<$J$8,I48+1/12,""),"") -> 2.75 | J49: =IF(I49<>"",J48+1/12,"") -> 67.75 | K49: =IFERROR(VLOOKUP(J49,$B$3:$F$1060,3,TRUE),"") -> 0.015407333 | L49: =IF(I49<>"",1-K49,"") -> 0.98459267 | M49: =IF(I49<>"",M48*L48,"") -> 0.69241223 | N49: =IF(I49<>"",(1+$M$10)^-(1+I49),"") -> 0.72180924 | Q49: =IFERROR(IF(Q48+1/12<$J$8,Q48+1/12,""),"") -> 2.75 | R49: =IF(Q49<>"",R48*L48,"") -> 0.69241223 | S49: =IF(Q49<>"",(1+$M$10)^-(12*Q49),"") -> 0.056769808 | T49: =IFERROR(S49,"") -> 0.056769808
B50: =B49+1/12 -> 15.833333 | D50: =(B50-$B$40)*$D$40 -> 0.0004125 | E50: =E40-(10/12)*F40 -> 998305.58 | F50: =E50-E51 -> 41.197099 | G50: =1-D50 -> 0.9995875 | I50: =IFERROR(IF(I49+1/12<$J$8,I49+1/12,""),"") -> 2.8333333 | J50: =IF(I50<>"",J49+1/12,"") -> 67.833333 | K50: =IFERROR(VLOOKUP(J50,$B$3:$F$1060,3,TRUE),"") -> 0.01733325 | L50: =IF(I50<>"",1-K50,"") -> 0.98266675 | M50: =IF(I50<>"",M49*L49,"") -> 0.681744 | N50: =IF(I50<>"",(1+$M$10)^-(1+I50),"") -> 0.71659911 | Q50: =IFERROR(IF(Q49+1/12<$J$8,Q49+1/12,""),"") -> 2.8333333 | R50: =IF(Q50<>"",R49*L49,"") -> 0.681744 | S50: =IF(Q50<>"",(1+$M$10)^-(12*Q50),"") -> 0.05204313 | T50: =IFERROR(S50,"") -> 0.05204313
B51: =B50+1/12 -> 15.916667 | D51: =(B51-$B$40)*$D$40 -> 0.00045375 | E51: =E40-(11/12)*F40 -> 998264.38 | F51: =E51-E52 -> 41.197099 | G51: =1-D51 -> 0.99954625 | I51: =IFERROR(IF(I50+1/12<$J$8,I50+1/12,""),"") -> 2.9166667 | J51: =IF(I51<>"",J50+1/12,"") -> 67.916667 | K51: =IFERROR(VLOOKUP(J51,$B$3:$F$1060,3,TRUE),"") -> 0.019259167 | L51: =IF(I51<>"",1-K51,"") -> 0.98074083 | M51: =IF(I51<>"",M50*L50,"") -> 0.66992716 | N51: =IF(I51<>"",(1+$M$10)^-(1+I51),"") -> 0.7114266 | Q51: =IFERROR(IF(Q50+1/12<$J$8,Q50+1/12,""),"") -> 2.9166667 | R51: =IF(Q51<>"",R50*L50,"") -> 0.66992716 | S51: =IF(Q51<>"",(1+$M$10)^-(12*Q51),"") -> 0.047709997 | T51: =IFERROR(S51,"") -> 0.047709997
B52: 16 | C52: 0.533 | D52: =C52/1000 -> 0.000533 | E52: =E40-F40 -> 998223.18 | F52: =D52*E52 -> 532.05296 | G52: =1-D52 -> 0.999467 | I52: =IFERROR(IF(I51+1/12<$J$8,I51+1/12,""),"") -> 3 | J52: =IF(I52<>"",J51+1/12,"") -> 68 | K52: =IFERROR(VLOOKUP(J52,$B$3:$F$1060,3,TRUE),"") -> 0.021185083 | L52: =IF(I52<>"",1-K52,"") -> 0.97881492 | M52: =IF(I52<>"",M51*L51,"") -> 0.65702493 | N52: =IF(I52<>"",(1+$M$10)^-(1+I52),"") -> 0.70629142 | Q52: =IFERROR(IF(Q51+1/12<$J$8,Q51+1/12,""),"") -> 3 | R52: =IF(Q52<>"",R51*L51,"") -> 0.65702493 | S52: =IF(Q52<>"",(1+$M$10)^-(12*Q52),"") -> 0.043737643 | T52: =IFERROR(S52,"") -> 0.043737643
B53: =B52+1/12 -> 16.083333 | D53: =(B53-$B$52)*$D$52 -> 4.4416667e-05 | E53: =E52-(1/12)*F52 -> 998178.84 | F53: =E53-E54 -> 44.337746 | G53: =1-D53 -> 0.99995558 | I53: =IFERROR(IF(I52+1/12<$J$8,I52+1/12,""),"") -> 3.0833333 | J53: =IF(I53<>"",J52+1/12,"") -> 68.083333 | K53: =IFERROR(VLOOKUP(J53,$B$3:$F$1060,3,TRUE),"") -> 0.024851 | L53: =IF(I53<>"",1-K53,"") -> 0.975149 | M53: =IF(I53<>"",M52*L52,"") -> 0.6431058 | N53: =IF(I53<>"",(1+$M$10)^-(1+I53),"") -> 0.70119331 | Q53: =IFERROR(IF(Q52+1/12<$J$8,Q52+1/12,""),"") -> 3.0833333 | R53: =IF(Q53<>"",R52*L52,"") -> 0.6431058 | S53: =IF(Q53<>"",(1+$M$10)^-(12*Q53),"") -> 0.040096028 | T53: =IFERROR(S53,"") -> 0.040096028
B54: =B53+1/12 -> 16.166667 | D54: =(B54-$B$52)*$D$52 -> 8.8833333e-05 | E54: =E52-(2/12)*F52 -> 998134.51 | F54: =E54-E55 -> 44.337746 | G54: =1-D54 -> 0.99991117 | I54: =IFERROR(IF(I53+1/12<$J$8,I53+1/12,""),"") -> 3.1666667 | J54: =IF(I54<>"",J53+1/12,"") -> 68.166667 | K54: =IFERROR(VLOOKUP(J54,$B$3:$F$1060,3,TRUE),"") -> 0.0020709167 | L54: =IF(I54<>"",1-K54,"") -> 0.99792908 | M54: =IF(I54<>"",M53*L53,"") -> 0.62712398 | N54: =IF(I54<>"",(1+$M$10)^-(1+I54),"") -> 0.69613199 | Q54: =IFERROR(IF(Q53+1/12<$J$8,Q53+1/12,""),"") -> 3.1666667 | R54: =IF(Q54<>"",R53*L53,"") -> 0.62712398 | S54: =IF(Q54<>"",(1+$M$10)^-(12*Q54),"") -> 0.036757616 | T54: =IFERROR(S54,"") -> 0.036757616
B55: =B54+1/12 -> 16.25 | D55: =(B55-$B$52)*$D$52 -> 0.00013325 | E55: =E52-(3/12)*F52 -> 998090.17 | F55: =E55-E56 -> 44.337746 | G55: =1-D55 -> 0.99986675 | I55: =IFERROR(IF(I54+1/12<$J$8,I54+1/12,""),"") -> 3.25 | J55: =IF(I55<>"",J54+1/12,"") -> 68.25 | K55: =IFERROR(VLOOKUP(J55,$B$3:$F$1060,3,TRUE),"") -> 0.0041418333 | L55: =IF(I55<>"",1-K55,"") -> 0.99585817 | M55: =IF(I55<>"",M54*L54,"") -> 0.62582525 | N55: =IF(I55<>"",(1+$M$10)^-(1+I55),"") -> 0.69110721 | Q55: =IFERROR(IF(Q54+1/12<$J$8,Q54+1/12,""),"") -> 3.25 | R55: =IF(Q55<>"",R54*L54,"") -> 0.62582525 | S55: =IF(Q55<>"",(1+$M$10)^-(12*Q55),"") -> 0.033697161 | T55: =IFERROR(S55,"") -> 0.033697161
B56: =B55+1/12 -> 16.333333 | D56: =(B56-$B$52)*$D$52 -> 0.00017766667 | E56: =E52-(4/12)*F52 -> 998045.83 | F56: =E56-E57 -> 44.337746 | G56: =1-D56 -> 0.99982233 | I56: =IFERROR(IF(I55+1/12<$J$8,I55+1/12,""),"") -> 3.3333333 | J56: =IF(I56<>"",J55+1/12,"") -> 68.333333 | K56: =IFERROR(VLOOKUP(J56,$B$3:$F$1060,3,TRUE),"") -> 0.00621275 | L56: =IF(I56<>"",1-K56,"") -> 0.99378725 | M56: =IF(I56<>"",M55*L55,"") -> 0.62323319 | N56: =IF(I56<>"",(1+$M$10)^-(1+I56),"") -> 0.6861187 | Q56: =IFERROR(IF(Q55+1/12<$J$8,Q55+1/12,""),"") -> 3.3333333 | R56: =IF(Q56<>"",R55*L55,"") -> 0.62323319 | S56: =IF(Q56<>"",(1+$M$10)^-(12*Q56),"") -> 0.030891522 | T56: =IFERROR(S56,"") -> 0.030891522
B57: =B56+1/12 -> 16.416667 | D57: =(B57-$B$52)*$D$52 -> 0.00022208333 | E57: =E52-(5/12)*F52 -> 998001.49 | F57: =E57-E58 -> 44.337746 | G57: =1-D57 -> 0.99977792 | I57: =IFERROR(IF(I56+1/12<$J$8,I56+1/12,""),"") -> 3.4166667 | J57: =IF(I57<>"",J56+1/12,"") -> 68.416667 | K57: =IFERROR(VLOOKUP(J57,$B$3:$F$1060,3,TRUE),"") -> 0.0082836667 | L57: =IF(I57<>"",1-K57,"") -> 0.99171633 | M57: =IF(I57<>"",M56*L56,"") -> 0.6193612 | N57: =IF(I57<>"",(1+$M$10)^-(1+I57),"") -> 0.6811662 | Q57: =IFERROR(IF(Q56+1/12<$J$8,Q56+1/12,""),"") -> 3.4166667 | R57: =IF(Q57<>"",R56*L56,"") -> 0.6193612 | S57: =IF(Q57<>"",(1+$M$10)^-(12*Q57),"") -> 0.028319481 | T57: =IFERROR(S57,"") -> 0.028319481
B58: =B57+1/12 -> 16.5 | D58: =(B58-$B$52)*$D$52 -> 0.0002665 | E58: =E52-(6/12)*F52 -> 997957.16 | F58: =E58-E59 -> 44.337746 | G58: =1-D58 -> 0.9997335 | I58: =IFERROR(IF(I57+1/12<$J$8,I57+1/12,""),"") -> 3.5 | J58: =IF(I58<>"",J57+1/12,"") -> 68.5 | K58: =IFERROR(VLOOKUP(J58,$B$3:$F$1060,3,TRUE),"") -> 0.010354583 | L58: =IF(I58<>"",1-K58,"") -> 0.98964542 | M58: =IF(I58<>"",M57*L57,"") -> 0.61423062 | N58: =IF(I58<>"",(1+$M$10)^-(1+I58),"") -> 0.67624944 | Q58: =IFERROR(IF(Q57+1/12<$J$8,Q57+1/12,""),"") -> 3.5 | R58: =IF(Q58<>"",R57*L57,"") -> 0.61423062 | S58: =IF(Q58<>"",(1+$M$10)^-(12*Q58),"") -> 0.025961589 | T58: =IFERROR(S58,"") -> 0.025961589
B59: =B58+1/12 -> 16.583333 | D59: =(B59-$B$52)*$D$52 -> 0.00031091667 | E59: =E52-(7/12)*F52 -> 997912.82 | F59: =E59-E60 -> 44.337746 | G59: =1-D59 -> 0.99968908 | I59: =IFERROR(IF(I58+1/12<$J$8,I58+1/12,""),"") -> 3.5833333 | J59: =IF(I59<>"",J58+1/12,"") -> 68.583333 | K59: =IFERROR(VLOOKUP(J59,$B$3:$F$1060,3,TRUE),"") -> 0.0124255 | L59: =IF(I59<>"",1-K59,"") -> 0.9875745 | M59: =IF(I59<>"",M58*L58,"") -> 0.60787051 | N59: =IF(I59<>"",(1+$M$10)^-(1+I59),"") -> 0.67136818 | Q59: =IFERROR(IF(Q58+1/12<$J$8,Q58+1/12,""),"") -> 3.5833333 | R59: =IF(Q59<>"",R58*L58,"") -> 0.60787051 | S59: =IF(Q59<>"",(1+$M$10)^-(12*Q59),"") -> 0.023800016 | T59: =IFERROR(S59,"") -> 0.023800016
B60: =B59+1/12 -> 16.666667 | D60: =(B60-$B$52)*$D$52 -> 0.00035533333 | E60: =E52-(8/12)*F52 -> 997868.48 | F60: =E60-E61 -> 44.337746 | G60: =1-D60 -> 0.99964467 | I60: =IFERROR(IF(I59+1/12<$J$8,I59+1/12,""),"") -> 3.6666667 | J60: =IF(I60<>"",J59+1/12,"") -> 68.666667 | K60: =IFERROR(VLOOKUP(J60,$B$3:$F$1060,3,TRUE),"") -> 0.014496417 | L60: =IF(I60<>"",1-K60,"") -> 0.98550358 | M60: =IF(I60<>"",M59*L59,"") -> 0.60031742 | N60: =IF(I60<>"",(1+$M$10)^-(1+I60),"") -> 0.66652215 | Q60: =IFERROR(IF(Q59+1/12<$J$8,Q59+1/12,""),"") -> 3.6666667 | R60: =IF(Q60<>"",R59*L59,"") -> 0.60031742 | S60: =IF(Q60<>"",(1+$M$10)^-(12*Q60),"") -> 0.021818417 | T60: =IFERROR(S60,"") -> 0.021818417
B61: =B60+1/12 -> 16.75 | D61: =(B61-$B$52)*$D$52 -> 0.00039975 | E61: =E52-(9/12)*F52 -> 997824.14 | F61: =E61-E62 -> 44.337746 | G61: =1-D61 -> 0.99960025 | I61: =IFERROR(IF(I60+1/12<$J$8,I60+1/12,""),"") -> 3.75 | J61: =IF(I61<>"",J60+1/12,"") -> 68.75 | K61: =IFERROR(VLOOKUP(J61,$B$3:$F$1060,3,TRUE),"") -> 0.016567333 | L61: =IF(I61<>"",1-K61,"") -> 0.98343267 | M61: =IF(I61<>"",M60*L60,"") -> 0.59161497 | N61: =IF(I61<>"",(1+$M$10)^-(1+I61),"") -> 0.6617111 | Q61: =IFERROR(IF(Q60+1/12<$J$8,Q60+1/12,""),"") -> 3.75 | R61: =IF(Q61<>"",R60*L60,"") -> 0.59161497 | S61: =IF(Q61<>"",(1+$M$10)^-(12*Q61),"") -> 0.020001806 | T61: =IFERROR(S61,"") -> 0.020001806
B62: =B61+1/12 -> 16.833333 | D62: =(B62-$B$52)*$D$52 -> 0.00044416667 | E62: =E52-(10/12)*F52 -> 997779.8 | F62: =E62-E63 -> 44.337746 | G62: =1-D62 -> 0.99955583 | I62: =IFERROR(IF(I61+1/12<$J$8,I61+1/12,""),"") -> 3.8333333 | J62: =IF(I62<>"",J61+1/12,"") -> 68.833333 | K62: =IFERROR(VLOOKUP(J62,$B$3:$F$1060,3,TRUE),"") -> 0.01863825 | L62: =IF(I62<>"",1-K62,"") -> 0.98136175 | M62: =IF(I62<>"",M61*L61,"") -> 0.58181349 | N62: =IF(I62<>"",(1+$M$10)^-(1+I62),"") -> 0.65693477 | Q62: =IFERROR(IF(Q61+1/12<$J$8,Q61+1/12,""),"") -> 3.8333333 | R62: =IF(Q62<>"",R61*L61,"") -> 0.58181349 | S62: =IF(Q62<>"",(1+$M$10)^-(12*Q62),"") -> 0.018336447 | T62: =IFERROR(S62,"") -> 0.018336447
B63: =B62+1/12 -> 16.916667 | D63: =(B63-$B$52)*$D$52 -> 0.00048858333 | E63: =E52-(11/12)*F52 -> 997735.47 | F63: =E63-E64 -> 44.337746 | G63: =1-D63 -> 0.99951142 | I63: =IFERROR(IF(I62+1/12<$J$8,I62+1/12,""),"") -> 3.9166667 | J63: =IF(I63<>"",J62+1/12,"") -> 68.916667 | K63: =IFERROR(VLOOKUP(J63,$B$3:$F$1060,3,TRUE),"") -> 0.020709167 | L63: =IF(I63<>"",1-K63,"") -> 0.97929083 | M63: =IF(I63<>"",M62*L62,"") -> 0.5709695 | N63: =IF(I63<>"",(1+$M$10)^-(1+I63),"") -> 0.65219292 | Q63: =IFERROR(IF(Q62+1/12<$J$8,Q62+1/12,""),"") -> 3.9166667 | R63: =IF(Q63<>"",R62*L62,"") -> 0.5709695 | S63: =IF(Q63<>"",(1+$M$10)^-(12*Q63),"") -> 0.016809747 | T63: =IFERROR(S63,"") -> 0.016809747
B64: 17 | C64: 0.575 | D64: =C64/1000 -> 0.000575 | E64: =E52-F52 -> 997691.13 | F64: =D64*E64 -> 573.6724 | G64: =1-D64 -> 0.999425 | I64: =IFERROR(IF(I63+1/12<$J$8,I63+1/12,""),"") -> 4 | J64: =IF(I64<>"",J63+1/12,"") -> 69 | K64: =IFERROR(VLOOKUP(J64,$B$3:$F$1060,3,TRUE),"") -> 0.022780083 | L64: =IF(I64<>"",1-K64,"") -> 0.97721992 | M64: =IF(I64<>"",M63*L63,"") -> 0.5591452 | N64: =IF(I64<>"",(1+$M$10)^-(1+I64),"") -> 0.6474853 | Q64: =IFERROR(IF(Q63+1/12<$J$8,Q63+1/12,""),"") -> 4 | R64: =IF(Q64<>"",R63*L63,"") -> 0.5591452 | S64: =IF(Q64<>"",(1+$M$10)^-(12*Q64),"") -> 0.01541016 | T64: =IFERROR(S64,"") -> 0.01541016
B65: =B64+1/12 -> 17.083333 | D65: =(B65-$B$64)*$D$64 -> 4.7916667e-05 | E65: =E64-(1/12)*F64 -> 997643.32 | F65: =E65-E66 -> 47.806033 | G65: =1-D65 -> 0.99995208 | I65: =IFERROR(IF(I64+1/12<$J$8,I64+1/12,""),"") -> 4.0833333 | J65: =IF(I65<>"",J64+1/12,"") -> 69.083333 | K65: =IFERROR(VLOOKUP(J65,$B$3:$F$1060,3,TRUE),"") -> 0.02672 | L65: =IF(I65<>"",1-K65,"") -> 0.97328 | M65: =IF(I65<>"",M64*L64,"") -> 0.54640782 | N65: =IF(I65<>"",(1+$M$10)^-(1+I65),"") -> 0.64281166 | Q65: =IFERROR(IF(Q64+1/12<$J$8,Q64+1/12,""),"") -> 4.0833333 | R65: =IF(Q65<>"",R64*L64,"") -> 0.54640782 | S65: =IF(Q65<>"",(1+$M$10)^-(12*Q65),"") -> 0.014127104 | T65: =IFERROR(S65,"") -> 0.014127104
B66: =B65+1/12 -> 17.166667 | D66: =(B66-$B$64)*$D$64 -> 9.5833333e-05 | E66: =E64-(2/12)*F64 -> 997595.52 | F66: =E66-E67 -> 47.806033 | G66: =1-D66 -> 0.99990417 | I66: =IFERROR(IF(I65+1/12<$J$8,I65+1/12,""),"") -> 4.1666667 | J66: =IF(I66<>"",J65+1/12,"") -> 69.166667 | K66: =IFERROR(VLOOKUP(J66,$B$3:$F$1060,3,TRUE),"") -> 0.0022266667 | L66: =IF(I66<>"",1-K66,"") -> 0.99777333 | M66: =IF(I66<>"",M65*L65,"") -> 0.53180781 | N66: =IF(I66<>"",(1+$M$10)^-(1+I66),"") -> 0.63817175 | Q66: =IFERROR(IF(Q65+1/12<$J$8,Q65+1/12,""),"") -> 4.1666667 | R66: =IF(Q66<>"",R65*L65,"") -> 0.53180781 | S66: =IF(Q66<>"",(1+$M$10)^-(12*Q66),"") -> 0.012950875 | T66: =IFERROR(S66,"") -> 0.012950875
B67: =B66+1/12 -> 17.25 | D67: =(B67-$B$64)*$D$64 -> 0.00014375 | E67: =E64-(3/12)*F64 -> 997547.71 | F67: =E67-E68 -> 47.806033 | G67: =1-D67 -> 0.99985625 | I67: =IFERROR(IF(I66+1/12<$J$8,I66+1/12,""),"") -> 4.25 | J67: =IF(I67<>"",J66+1/12,"") -> 69.25 | K67: =IFERROR(VLOOKUP(J67,$B$3:$F$1060,3,TRUE),"") -> 0.0044533333 | L67: =IF(I67<>"",1-K67,"") -> 0.99554667 | M67: =IF(I67<>"",M66*L66,"") -> 0.53062365 | N67: =IF(I67<>"",(1+$M$10)^-(1+I67),"") -> 0.63356534 | Q67: =IFERROR(IF(Q66+1/12<$J$8,Q66+1/12,""),"") -> 4.25 | R67: =IF(Q67<>"",R66*L66,"") -> 0.53062365 | S67: =IF(Q67<>"",(1+$M$10)^-(12*Q67),"") -> 0.01187258 | T67: =IFERROR(S67,"") -> 0.01187258
B68: =B67+1/12 -> 17.333333 | D68: =(B68-$B$64)*$D$64 -> 0.00019166667 | E68: =E64-(4/12)*F64 -> 997499.91 | F68: =E68-E69 -> 47.806033 | G68: =1-D68 -> 0.99980833 | I68: =IFERROR(IF(I67+1/12<$J$8,I67+1/12,""),"") -> 4.3333333 | J68: =IF(I68<>"",J67+1/12,"") -> 69.333333 | K68: =IFERROR(VLOOKUP(J68,$B$3:$F$1060,3,TRUE),"") -> 0.00668 | L68: =IF(I68<>"",1-K68,"") -> 0.99332 | M68: =IF(I68<>"",M67*L67,"") -> 0.5282606 | N68: =IF(I68<>"",(1+$M$10)^-(1+I68),"") -> 0.62899217 | Q68: =IFERROR(IF(Q67+1/12<$J$8,Q67+1/12,""),"") -> 4.3333333 | R68: =IF(Q68<>"",R67*L67,"") -> 0.5282606 | S68: =IF(Q68<>"",(1+$M$10)^-(12*Q68),"") -> 0.010884064 | T68: =IFERROR(S68,"") -> 0.010884064
B69: =B68+1/12 -> 17.416667 | D69: =(B69-$B$64)*$D$64 -> 0.00023958333 | E69: =E64-(5/12)*F64 -> 997452.1 | F69: =E69-E70 -> 47.806033 | G69: =1-D69 -> 0.99976042 | I69: =IFERROR(IF(I68+1/12<$J$8,I68+1/12,""),"") -> 4.4166667 | J69: =IF(I69<>"",J68+1/12,"") -> 69.416667 | K69: =IFERROR(VLOOKUP(J69,$B$3:$F$1060,3,TRUE),"") -> 0.0089066667 | L69: =IF(I69<>"",1-K69,"") -> 0.99109333 | M69: =IF(I69<>"",M68*L68,"") -> 0.52473182 | N69: =IF(I69<>"",(1+$M$10)^-(1+I69),"") -> 0.62445202 | Q69: =IFERROR(IF(Q68+1/12<$J$8,Q68+1/12,""),"") -> 4.4166667 | R69: =IF(Q69<>"",R68*L68,"") -> 0.52473182 | S69: =IF(Q69<>"",(1+$M$10)^-(12*Q69),"") -> 0.0099778524 | T69: =IFERROR(S69,"") -> 0.0099778524
B70: =B69+1/12 -> 17.5 | D70: =(B70-$B$64)*$D$64 -> 0.0002875 | E70: =E64-(6/12)*F64 -> 997404.29 | F70: =E70-E71 -> 47.806033 | G70: =1-D70 -> 0.9997125 | I70: =IFERROR(IF(I69+1/12<$J$8,I69+1/12,""),"") -> 4.5 | J70: =IF(I70<>"",J69+1/12,"") -> 69.5 | K70: =IFERROR(VLOOKUP(J70,$B$3:$F$1060,3,TRUE),"") -> 0.011133333 | L70: =IF(I70<>"",1-K70,"") -> 0.98886667 | M70: =IF(I70<>"",M69*L69,"") -> 0.52005821 | N70: =IF(I70<>"",(1+$M$10)^-(1+I70),"") -> 0.61994463 | Q70: =IFERROR(IF(Q69+1/12<$J$8,Q69+1/12,""),"") -> 4.5 | R70: =IF(Q70<>"",R69*L69,"") -> 0.52005821 | S70: =IF(Q70<>"",(1+$M$10)^-(12*Q70),"") -> 0.0091470922 | T70: =IFERROR(S70,"") -> 0.0091470922
B71: =B70+1/12 -> 17.583333 | D71: =(B71-$B$64)*$D$64 -> 0.00033541667 | E71: =E64-(7/12)*F64 -> 997356.49 | F71: =E71-E72 -> 47.806033 | G71: =1-D71 -> 0.99966458 | I71: =IFERROR(IF(I70+1/12<$J$8,I70+1/12,""),"") -> 4.5833333 | J71: =IF(I71<>"",J70+1/12,"") -> 69.583333 | K71: =IFERROR(VLOOKUP(J71,$B$3:$F$1060,3,TRUE),"") -> 0.01336 | L71: =IF(I71<>"",1-K71,"") -> 0.98664 | M71: =IF(I71<>"",M70*L70,"") -> 0.51426823 | N71: =IF(I71<>"",(1+$M$10)^-(1+I71),"") -> 0.61546978 | Q71: =IFERROR(IF(Q70+1/12<$J$8,Q70+1/12,""),"") -> 4.5833333 | R71: =IF(Q71<>"",R70*L70,"") -> 0.51426823 | S71: =IF(Q71<>"",(1+$M$10)^-(12*Q71),"") -> 0.0083855015 | T71: =IFERROR(S71,"") -> 0.0083855015
B72: =B71+1/12 -> 17.666667 | D72: =(B72-$B$64)*$D$64 -> 0.00038333333 | E72: =E64-(8/12)*F64 -> 997308.68 | F72: =E72-E73 -> 47.806033 | G72: =1-D72 -> 0.99961667 | I72: =IFERROR(IF(I71+1/12<$J$8,I71+1/12,""),"") -> 4.6666667 | J72: =IF(I72<>"",J71+1/12,"") -> 69.666667 | K72: =IFERROR(VLOOKUP(J72,$B$3:$F$1060,3,TRUE),"") -> 0.015586667 | L72: =IF(I72<>"",1-K72,"") -> 0.98441333 | M72: =IF(I72<>"",M71*L71,"") -> 0.50739761 | N72: =IF(I72<>"",(1+$M$10)^-(1+I72),"") -> 0.61102723 | Q72: =IFERROR(IF(Q71+1/12<$J$8,Q71+1/12,""),"") -> 4.6666667 | R72: =IF(Q72<>"",R71*L71,"") -> 0.50739761 | S72: =IF(Q72<>"",(1+$M$10)^-(12*Q72),"") -> 0.0076873211 | T72: =IFERROR(S72,"") -> 0.0076873211
B73: =B72+1/12 -> 17.75 | D73: =(B73-$B$64)*$D$64 -> 0.00043125 | E73: =E64-(9/12)*F64 -> 997260.88 | F73: =E73-E74 -> 47.806033 | G73: =1-D73 -> 0.99956875 | I73: =IFERROR(IF(I72+1/12<$J$8,I72+1/12,""),"") -> 4.75 | J73: =IF(I73<>"",J72+1/12,"") -> 69.75 | K73: =IFERROR(VLOOKUP(J73,$B$3:$F$1060,3,TRUE),"") -> 0.017813333 | L73: =IF(I73<>"",1-K73,"") -> 0.98218667 | M73: =IF(I73<>"",M72*L72,"") -> 0.49948897 | N73: =IF(I73<>"",(1+$M$10)^-(1+I73),"") -> 0.60661675 | Q73: =IFERROR(IF(Q72+1/12<$J$8,Q72+1/12,""),"") -> 4.75 | R73: =IF(Q73<>"",R72*L72,"") -> 0.49948897 | S73: =IF(Q73<>"",(1+$M$10)^-(12*Q73),"") -> 0.0070472715 | T73: =IFERROR(S73,"") -> 0.0070472715
B74: =B73+1/12 -> 17.833333 | D74: =(B74-$B$64)*$D$64 -> 0.00047916667 | E74: =E64-(10/12)*F64 -> 997213.07 | F74: =E74-E75 -> 47.806033 | G74: =1-D74 -> 0.99952083 | I74: =IFERROR(IF(I73+1/12<$J$8,I73+1/12,""),"") -> 4.8333333 | J74: =IF(I74<>"",J73+1/12,"") -> 69.833333 | K74: =IFERROR(VLOOKUP(J74,$B$3:$F$1060,3,TRUE),"") -> 0.02004 | L74: =IF(I74<>"",1-K74,"") -> 0.97996 | M74: =IF(I74<>"",M73*L73,"") -> 0.49059141 | N74: =IF(I74<>"",(1+$M$10)^-(1+I74),"") -> 0.60223811 | Q74: =IFERROR(IF(Q73+1/12<$J$8,Q73+1/12,""),"") -> 4.8333333 | R74: =IF(Q74<>"",R73*L73,"") -> 0.49059141 | S74: =IF(Q74<>"",(1+$M$10)^-(12*Q74),"") -> 0.0064605127 | T74: =IFERROR(S74,"") -> 0.0064605127
B75: =B74+1/12 -> 17.916667 | D75: =(B75-$B$64)*$D$64 -> 0.00052708333 | E75: =E64-(11/12)*F64 -> 997165.26 | F75: =E75-E76 -> 47.806033 | G75: =1-D75 -> 0.99947292 | I75: =IFERROR(IF(I74+1/12<$J$8,I74+1/12,""),"") -> 4.9166667 | J75: =IF(I75<>"",J74+1/12,"") -> 69.916667 | K75: =IFERROR(VLOOKUP(J75,$B$3:$F$1060,3,TRUE),"") -> 0.022266667 | L75: =IF(I75<>"",1-K75,"") -> 0.97773333 | M75: =IF(I75<>"",M74*L74,"") -> 0.48075995 | N75: =IF(I75<>"",(1+$M$10)^-(1+I75),"") -> 0.59789107 | Q75: =IFERROR(IF(Q74+1/12<$J$8,Q74+1/12,""),"") -> 4.9166667 | R75: =IF(Q75<>"",R74*L74,"") -> 0.48075995 | S75: =IF(Q75<>"",(1+$M$10)^-(12*Q75),"") -> 0.0059226077 | T75: =IFERROR(S75,"") -> 0.0059226077
B76: 18 | C76: 0.619 | D76: =C76/1000 -> 0.000619 | E76: =E64-F64 -> 997117.46 | F76: =D76*E76 -> 617.21571 | G76: =1-D76 -> 0.999381 | I76: =IFERROR(IF(I75+1/12<$J$8,I75+1/12,""),"") -> 5 | J76: =IF(I76<>"",J75+1/12,"") -> 70 | K76: =IFERROR(VLOOKUP(J76,$B$3:$F$1060,3,TRUE),"") -> 0.024493333 | L76: =IF(I76<>"",1-K76,"") -> 0.97550667 | M76: =IF(I76<>"",M75*L75,"") -> 0.47005503 | N76: =IF(I76<>"",(1+$M$10)^-(1+I76),"") -> 0.5935754 | Q76: =IFERROR(IF(Q75+1/12<$J$8,Q75+1/12,""),"") -> 5 | R76: =IF(Q76<>"",R75*L75,"") -> 0.47005503 | S76: =IF(Q76<>"",(1+$M$10)^-(12*Q76),"") -> 0.0054294889 | T76: =IFERROR(S76*R76,"") -> 0.0025521586
B77: =B76+1/12 -> 18.083333 | D77: =(B77-$B$76)*$D$76 -> 5.1583333e-05 | E77: =E76-(1/12)*F76 -> 997066.02 | F77: =E77-E78 -> 51.434642 | G77: =1-D77 -> 0.99994842 | I77: =IFERROR(IF(I76+1/12<$J$8,I76+1/12,""),"") -> 5.0833333 | J77: =IF(I77<>"",J76+1/12,"") -> 70.083333 | K77: =IFERROR(VLOOKUP(J77,$B$3:$F$1060,3,TRUE),"") -> 0.028724 | L77: =IF(I77<>"",1-K77,"") -> 0.971276 | M77: =IF(I77<>"",M76*L76,"") -> 0.45854182 | N77: =IF(I77<>"",(1+$M$10)^-(1+I77),"") -> 0.58929089 | Q77: =IFERROR(IF(Q76+1/12<$J$8,Q76+1/12,""),"") -> 5.0833333 | R77: =IF(Q77<>"",R76*L76,"") -> 0.45854182 | S77: =IF(Q77<>"",(1+$M$10)^-(12*Q77),"") -> 0.0049774274 | T77: =IFERROR(S77*R77,"") -> 0.0022823586
B78: =B77+1/12 -> 18.166667 | D78: =(B78-$B$76)*$D$76 -> 0.00010316667 | E78: =E76-(2/12)*F76 -> 997014.59 | F78: =E78-E79 -> 51.434642 | G78: =1-D78 -> 0.99989683 | I78: =IFERROR(IF(I77+1/12<$J$8,I77+1/12,""),"") -> 5.1666667 | J78: =IF(I78<>"",J77+1/12,"") -> 70.166667 | K78: =IFERROR(VLOOKUP(J78,$B$3:$F$1060,3,TRUE),"") -> 0.0023936667 | L78: =IF(I78<>"",1-K78,"") -> 0.99760633 | M78: =IF(I78<>"",M77*L77,"") -> 0.44537066 | N78: =IF(I78<>"",(1+$M$10)^-(1+I78),"") -> 0.5850373 | Q78: =IFERROR(IF(Q77+1/12<$J$8,Q77+1/12,""),"") -> 5.1666667 | R78: =IF(Q78<>"",R77*L77,"") -> 0.44537066 | S78: =IF(Q78<>"",(1+$M$10)^-(12*Q78),"") -> 0.0045630047 | T78: =IFERROR(S78*R78,"") -> 0.0020322284
B79: =B78+1/12 -> 18.25 | D79: =(B79-$B$76)*$D$76 -> 0.00015475 | E79: =E76-(3/12)*F76 -> 996963.15 | F79: =E79-E80 -> 51.434642 | G79: =1-D79 -> 0.99984525 | I79: =IFERROR(IF(I78+1/12<$J$8,I78+1/12,""),"") -> 5.25 | J79: =IF(I79<>"",J78+1/12,"") -> 70.25 | K79: =IFERROR(VLOOKUP(J79,$B$3:$F$1060,3,TRUE),"") -> 0.0047873333 | L79: =IF(I79<>"",1-K79,"") -> 0.99521267 | M79: =IF(I79<>"",M78*L78,"") -> 0.44430459 | N79: =IF(I79<>"",(1+$M$10)^-(1+I79),"") -> 0.58081442 | Q79: =IFERROR(IF(Q78+1/12<$J$8,Q78+1/12,""),"") -> 5.25 | R79: =IF(Q79<>"",R78*L78,"") -> 0.44430459 | S79: =IF(Q79<>"",(1+$M$10)^-(12*Q79),"") -> 0.004183087 | T79: =IFERROR(S79*R79,"") -> 0.0018585648
B80: =B79+1/12 -> 18.333333 | D80: =(B80-$B$76)*$D$76 -> 0.00020633333 | E80: =E76-(4/12)*F76 -> 996911.72 | F80: =E80-E81 -> 51.434642 | G80: =1-D80 -> 0.99979367 | I80: =IFERROR(IF(I79+1/12<$J$8,I79+1/12,""),"") -> 5.3333333 | J80: =IF(I80<>"",J79+1/12,"") -> 70.333333 | K80: =IFERROR(VLOOKUP(J80,$B$3:$F$1060,3,TRUE),"") -> 0.007181 | L80: =IF(I80<>"",1-K80,"") -> 0.992819 | M80: =IF(I80<>"",M79*L79,"") -> 0.44217756 | N80: =IF(I80<>"",(1+$M$10)^-(1+I80),"") -> 0.57662202 | Q80: =IFERROR(IF(Q79+1/12<$J$8,Q79+1/12,""),"") -> 5.3333333 | R80: =IF(Q80<>"",R79*L79,"") -> 0.44217756 | S80: =IF(Q80<>"",(1+$M$10)^-(12*Q80),"") -> 0.0038348014 | T80: =IFERROR(S80*R80,"") -> 0.0016956631
B81: =B80+1/12 -> 18.416667 | D81: =(B81-$B$76)*$D$76 -> 0.00025791667 | E81: =E76-(5/12)*F76 -> 996860.28 | F81: =E81-E82 -> 51.434642 | G81: =1-D81 -> 0.99974208 | I81: =IFERROR(IF(I80+1/12<$J$8,I80+1/12,""),"") -> 5.4166667 | J81: =IF(I81<>"",J80+1/12,"") -> 70.416667 | K81: =IFERROR(VLOOKUP(J81,$B$3:$F$1060,3,TRUE),"") -> 0.0095746667 | L81: =IF(I81<>"",1-K81,"") -> 0.99042533 | M81: =IF(I81<>"",M80*L80,"") -> 0.43900228 | N81: =IF(I81<>"",(1+$M$10)^-(1+I81),"") -> 0.57245988 | Q81: =IFERROR(IF(Q80+1/12<$J$8,Q80+1/12,""),"") -> 5.4166667 | R81: =IF(Q81<>"",R80*L80,"") -> 0.43900228 | S81: =IF(Q81<>"",(1+$M$10)^-(12*Q81),"") -> 0.0035155143 | T81: =IFERROR(S81*R81,"") -> 0.0015433188
B82: =B81+1/12 -> 18.5 | D82: =(B82-$B$76)*$D$76 -> 0.0003095 | E82: =E76-(6/12)*F76 -> 996808.85 | F82: =E82-E83 -> 51.434642 | G82: =1-D82 -> 0.9996905 | I82: =IFERROR(IF(I81+1/12<$J$8,I81+1/12,""),"") -> 5.5 | J82: =IF(I82<>"",J81+1/12,"") -> 70.5 | K82: =IFERROR(VLOOKUP(J82,$B$3:$F$1060,3,TRUE),"") -> 0.011968333 | L82: =IF(I82<>"",1-K82,"") -> 0.98803167 | M82: =IF(I82<>"",M81*L81,"") -> 0.43479898 | N82: =IF(I82<>"",(1+$M$10)^-(1+I82),"") -> 0.56832778 | Q82: =IFERROR(IF(Q81+1/12<$J$8,Q81+1/12,""),"") -> 5.5 | R82: =IF(Q82<>"",R81*L81,"") -> 0.43479898 | S82: =IF(Q82<>"",(1+$M$10)^-(12*Q82),"") -> 0.0032228111 | T82: =IFERROR(S82*R82,"") -> 0.001401275
B83: =B82+1/12 -> 18.583333 | D83: =(B83-$B$76)*$D$76 -> 0.00036108333 | E83: =E76-(7/12)*F76 -> 996757.41 | F83: =E83-E84 -> 51.434642 | G83: =1-D83 -> 0.99963892 | I83: =IFERROR(IF(I82+1/12<$J$8,I82+1/12,""),"") -> 5.5833333 | J83: =IF(I83<>"",J82+1/12,"") -> 70.583333 | K83: =IFERROR(VLOOKUP(J83,$B$3:$F$1060,3,TRUE),"") -> 0.014362 | L83: =IF(I83<>"",1-K83,"") -> 0.985638 | M83: =IF(I83<>"",M82*L82,"") -> 0.42959516 | N83: =IF(I83<>"",(1+$M$10)^-(1+I83),"") -> 0.56422551 | Q83: =IFERROR(IF(Q82+1/12<$J$8,Q82+1/12,""),"") -> 5.5833333 | R83: =IF(Q83<>"",R82*L82,"") -> 0.42959516 | S83: =IF(Q83<>"",(1+$M$10)^-(12*Q83),"") -> 0.0029544785 | T83: =IFERROR(S83*R83,"") -> 0.0012692297
B84: =B83+1/12 -> 18.666667 | D84: =(B84-$B$76)*$D$76 -> 0.00041266667 | E84: =E76-(8/12)*F76 -> 996705.98 | F84: =E84-E85 -> 51.434642 | G84: =1-D84 -> 0.99958733 | I84: =IFERROR(IF(I83+1/12<$J$8,I83+1/12,""),"") -> 5.6666667 | J84: =IF(I84<>"",J83+1/12,"") -> 70.666667 | K84: =IFERROR(VLOOKUP(J84,$B$3:$F$1060,3,TRUE),"") -> 0.016755667 | L84: =IF(I84<>"",1-K84,"") -> 0.98324433 | M84: =IF(I84<>"",M83*L83,"") -> 0.42342532 | N84: =IF(I84<>"",(1+$M$10)^-(1+I84),"") -> 0.56015285 | Q84: =IFERROR(IF(Q83+1/12<$J$8,Q83+1/12,""),"") -> 5.6666667 | R84: =IF(Q84<>"",R83*L83,"") -> 0.42342532 | S84: =IF(Q84<>"",(1+$M$10)^-(12*Q84),"") -> 0.0027084874 | T84: =IFERROR(S84*R84,"") -> 0.0011468421
B85: =B84+1/12 -> 18.75 | D85: =(B85-$B$76)*$D$76 -> 0.00046425 | E85: =E76-(9/12)*F76 -> 996654.55 | F85: =E85-E86 -> 51.434642 | G85: =1-D85 -> 0.99953575 | I85: =IFERROR(IF(I84+1/12<$J$8,I84+1/12,""),"") -> 5.75 | J85: =IF(I85<>"",J84+1/12,"") -> 70.75 | K85: =IFERROR(VLOOKUP(J85,$B$3:$F$1060,3,TRUE),"") -> 0.019149333 | L85: =IF(I85<>"",1-K85,"") -> 0.98085067 | M85: =IF(I85<>"",M84*L84,"") -> 0.41633054 | N85: =IF(I85<>"",(1+$M$10)^-(1+I85),"") -> 0.55610959 | Q85: =IFERROR(IF(Q84+1/12<$J$8,Q84+1/12,""),"") -> 5.75 | R85: =IF(Q85<>"",R84*L84,"") -> 0.41633054 | S85: =IF(Q85<>"",(1+$M$10)^-(12*Q85),"") -> 0.0024829776 | T85: =IFERROR(S85*R85,"") -> 0.0010337394
B86: =B85+1/12 -> 18.833333 | D86: =(B86-$B$76)*$D$76 -> 0.00051583333 | E86: =E76-(10/12)*F76 -> 996603.11 | F86: =E86-E87 -> 51.434642 | G86: =1-D86 -> 0.99948417 | I86: =IFERROR(IF(I85+1/12<$J$8,I85+1/12,""),"") -> 5.8333333 | J86: =IF(I86<>"",J85+1/12,"") -> 70.833333 | K86: =IFERROR(VLOOKUP(J86,$B$3:$F$1060,3,TRUE),"") -> 0.021543 | L86: =IF(I86<>"",1-K86,"") -> 0.978457 | M86: =IF(I86<>"",M85*L85,"") -> 0.40835809 | N86: =IF(I86<>"",(1+$M$10)^-(1+I86),"") -> 0.55209551 | Q86: =IFERROR(IF(Q85+1/12<$J$8,Q85+1/12,""),"") -> 5.8333333 | R86: =IF(Q86<>"",R85*L85,"") -> 0.40835809 | S86: =IF(Q86<>"",(1+$M$10)^-(12*Q86),"") -> 0.0022762438 | T86: =IFERROR(S86*R86,"") -> 0.00092952258
B87: =B86+1/12 -> 18.916667 | D87: =(B87-$B$76)*$D$76 -> 0.00056741667 | E87: =E76-(11/12)*F76 -> 996551.68 | F87: =E87-E88 -> 51.434642 | G87: =1-D87 -> 0.99943258 | I87: =IFERROR(IF(I86+1/12<$J$8,I86+1/12,""),"") -> 5.9166667 | J87: =IF(I87<>"",J86+1/12,"") -> 70.916667 | K87: =IFERROR(VLOOKUP(J87,$B$3:$F$1060,3,TRUE),"") -> 0.023936667 | L87: =IF(I87<>"",1-K87,"") -> 0.97606333 | M87: =IF(I87<>"",M86*L86,"") -> 0.39956083 | N87: =IF(I87<>"",(1+$M$10)^-(1+I87),"") -> 0.5481104 | Q87: =IFERROR(IF(Q86+1/12<$J$8,Q86+1/12,""),"") -> 5.9166667 | R87: =IF(Q87<>"",R86*L86,"") -> 0.39956083 | S87: =IF(Q87<>"",(1+$M$10)^-(12*Q87),"") -> 0.0020867228 | T87: =IFERROR(S87*R87,"") -> 0.0008337727
B88: 19 | C88: 0.667 | D88: =C88/1000 -> 0.000667 | E88: =E76-F76 -> 996500.24 | F88: =D88*E88 -> 664.66566 | G88: =1-D88 -> 0.999333 | I88: =IFERROR(IF(I87+1/12<$J$8,I87+1/12,""),"") -> 6 | J88: =IF(I88<>"",J87+1/12,"") -> 71 | K88: =IFERROR(VLOOKUP(J88,$B$3:$F$1060,3,TRUE),"") -> 0.026330333 | L88: =IF(I88<>"",1-K88,"") -> 0.97366967 | M88: =IF(I88<>"",M87*L87,"") -> 0.38999668 | N88: =IF(I88<>"",(1+$M$10)^-(1+I88),"") -> 0.54415406 | Q88: =IFERROR(IF(Q87+1/12<$J$8,Q87+1/12,""),"") -> 6 | R88: =IF(Q88<>"",R87*L87,"") -> 0.38999668 | S88: =IF(Q88<>"",(1+$M$10)^-(12*Q88),"") -> 0.0019129814 | T88: =IFERROR(S88*R88,"") -> 0.00074605638
B89: =B88+1/12 -> 19.083333 | D89: =(B89-$B$88)*$D$88 -> 5.5583333e-05 | E89: =E88-(1/12)*F88 -> 996444.85 | F89: =E89-E90 -> 55.388805 | G89: =1-D89 -> 0.99994442 | I89: =IFERROR(IF(I88+1/12<$J$8,I88+1/12,""),"") -> 6.0833333 | J89: =IF(I89<>"",J88+1/12,"") -> 71.083333 | K89: =IFERROR(VLOOKUP(J89,$B$3:$F$1060,3,TRUE),"") -> 0.030874 | L89: =IF(I89<>"",1-K89,"") -> 0.969126 | M89: =IF(I89<>"",M88*L88,"") -> 0.37972794 | N89: =IF(I89<>"",(1+$M$10)^-(1+I89),"") -> 0.54022628 | Q89: =IFERROR(IF(Q88+1/12<$J$8,Q88+1/12,""),"") -> 6.0833333 | R89: =IF(Q89<>"",R88*L88,"") -> 0.37972794 | S89: =IF(Q89<>"",(1+$M$10)^-(12*Q89),"") -> 0.0017537057 | T89: =IFERROR(S89*R89,"") -> 0.00066593106
B90: =B89+1/12 -> 19.166667 | D90: =(B90-$B$88)*$D$88 -> 0.00011116667 | E90: =E88-(2/12)*F88 -> 996389.46 | F90: =E90-E91 -> 55.388805 | G90: =1-D90 -> 0.99988883 | I90: =IFERROR(IF(I89+1/12<$J$8,I89+1/12,""),"") -> 6.1666667 | J90: =IF(I90<>"",J89+1/12,"") -> 71.166667 | K90: =IFERROR(VLOOKUP(J90,$B$3:$F$1060,3,TRUE),"") -> 0.0025728333 | L90: =IF(I90<>"",1-K90,"") -> 0.99742717 | M90: =IF(I90<>"",M89*L89,"") -> 0.36800422 | N90: =IF(I90<>"",(1+$M$10)^-(1+I90),"") -> 0.53632685 | Q90: =IFERROR(IF(Q89+1/12<$J$8,Q89+1/12,""),"") -> 6.1666667 | R90: =IF(Q90<>"",R89*L89,"") -> 0.36800422 | S90: =IF(Q90<>"",(1+$M$10)^-(12*Q90),"") -> 0.0016076915 | T90: =IFERROR(S90*R90,"") -> 0.00059163724
B91: =B90+1/12 -> 19.25 | D91: =(B91-$B$88)*$D$88 -> 0.00016675 | E91: =E88-(3/12)*F88 -> 996334.07 | F91: =E91-E92 -> 55.388805 | G91: =1-D91 -> 0.99983325 | I91: =IFERROR(IF(I90+1/12<$J$8,I90+1/12,""),"") -> 6.25 | J91: =IF(I91<>"",J90+1/12,"") -> 71.25 | K91: =IFERROR(VLOOKUP(J91,$B$3:$F$1060,3,TRUE),"") -> 0.0051456667 | L91: =IF(I91<>"",1-K91,"") -> 0.99485433 | M91: =IF(I91<>"",M90*L90,"") -> 0.3670574 | N91: =IF(I91<>"",(1+$M$10)^-(1+I91),"") -> 0.53245557 | Q91: =IFERROR(IF(Q90+1/12<$J$8,Q90+1/12,""),"") -> 6.25 | R91: =IF(Q91<>"",R90*L90,"") -> 0.3670574 | S91: =IF(Q91<>"",(1+$M$10)^-(12*Q91),"") -> 0.0014738344 | T91: =IFERROR(S91*R91,"") -> 0.00054098183
B92: =B91+1/12 -> 19.333333 | D92: =(B92-$B$88)*$D$88 -> 0.00022233333 | E92: =E88-(4/12)*F88 -> 996278.69 | F92: =E92-E93 -> 55.388805 | G92: =1-D92 -> 0.99977767 | I92: =IFERROR(IF(I91+1/12<$J$8,I91+1/12,""),"") -> 6.3333333 | J92: =IF(I92<>"",J91+1/12,"") -> 71.333333 | K92: =IFERROR(VLOOKUP(J92,$B$3:$F$1060,3,TRUE),"") -> 0.0077185 | L92: =IF(I92<>"",1-K92,"") -> 0.9922815 | M92: =IF(I92<>"",M91*L91,"") -> 0.36516865 | N92: =IF(I92<>"",(1+$M$10)^-(1+I92),"") -> 0.52861223 | Q92: =IFERROR(IF(Q91+1/12<$J$8,Q91+1/12,""),"") -> 6.3333333 | R92: =IF(Q92<>"",R91*L91,"") -> 0.36516865 | S92: =IF(Q92<>"",(1+$M$10)^-(12*Q92),"") -> 0.0013511223 | T92: =IFERROR(S92*R92,"") -> 0.00049338751
B93: =B92+1/12 -> 19.416667 | D93: =(B93-$B$88)*$D$88 -> 0.00027791667 | E93: =E88-(5/12)*F88 -> 996223.3 | F93: =E93-E94 -> 55.388805 | G93: =1-D93 -> 0.99972208 | I93: =IFERROR(IF(I92+1/12<$J$8,I92+1/12,""),"") -> 6.4166667 | J93: =IF(I93<>"",J92+1/12,"") -> 71.416667 | K93: =IFERROR(VLOOKUP(J93,$B$3:$F$1060,3,TRUE),"") -> 0.010291333 | L93: =IF(I93<>"",1-K93,"") -> 0.98970867 | M93: =IF(I93<>"",M92*L92,"") -> 0.36235009 | N93: =IF(I93<>"",(1+$M$10)^-(1+I93),"") -> 0.52479663 | Q93: =IFERROR(IF(Q92+1/12<$J$8,Q92+1/12,""),"") -> 6.4166667 | R93: =IF(Q93<>"",R92*L92,"") -> 0.36235009 | S93: =IF(Q93<>"",(1+$M$10)^-(12*Q93),"") -> 0.0012386273 | T93: =IFERROR(S93*R93,"") -> 0.00044881672
B94: =B93+1/12 -> 19.5 | D94: =(B94-$B$88)*$D$88 -> 0.0003335 | E94: =E88-(6/12)*F88 -> 996167.91 | F94: =E94-E95 -> 55.388805 | G94: =1-D94 -> 0.9996665 | I94: =IFERROR(IF(I93+1/12<$J$8,I93+1/12,""),"") -> 6.5 | J94: =IF(I94<>"",J93+1/12,"") -> 71.5 | K94: =IFERROR(VLOOKUP(J94,$B$3:$F$1060,3,TRUE),"") -> 0.012864167 | L94: =IF(I94<>"",1-K94,"") -> 0.98713583 | M94: =IF(I94<>"",M93*L93,"") -> 0.35862103 | N94: =IF(I94<>"",(1+$M$10)^-(1+I94),"") -> 0.52100857 | Q94: =IFERROR(IF(Q93+1/12<$J$8,Q93+1/12,""),"") -> 6.5 | R94: =IF(Q94<>"",R93*L93,"") -> 0.35862103 | S94: =IF(Q94<>"",(1+$M$10)^-(12*Q94),"") -> 0.0011354987 | T94: =IFERROR(S94*R94,"") -> 0.00040721371
B95: =B94+1/12 -> 19.583333 | D95: =(B95-$B$88)*$D$88 -> 0.00038908333 | E95: =E88-(7/12)*F88 -> 996112.52 | F95: =E95-E96 -> 55.388805 | G95: =1-D95 -> 0.99961092 | I95: =IFERROR(IF(I94+1/12<$J$8,I94+1/12,""),"") -> 6.5833333 | J95: =IF(I95<>"",J94+1/12,"") -> 71.583333 | K95: =IFERROR(VLOOKUP(J95,$B$3:$F$1060,3,TRUE),"") -> 0.015437 | L95: =IF(I95<>"",1-K95,"") -> 0.984563 | M95: =IF(I95<>"",M94*L94,"") -> 0.35400767 | N95: =IF(I95<>"",(1+$M$10)^-(1+I95),"") -> 0.51724786 | Q95: =IFERROR(IF(Q94+1/12<$J$8,Q94+1/12,""),"") -> 6.5833333 | R95: =IF(Q95<>"",R94*L94,"") -> 0.35400767 | S95: =IF(Q95<>"",(1+$M$10)^-(12*Q95),"") -> 0.0010409566 | T95: =IFERROR(S95*R95,"") -> 0.00036850661
B96: =B95+1/12 -> 19.666667 | D96: =(B96-$B$88)*$D$88 -> 0.00044466667 | E96: =E88-(8/12)*F88 -> 996057.13 | F96: =E96-E97 -> 55.388805 | G96: =1-D96 -> 0.99955533 | I96: =IFERROR(IF(I95+1/12<$J$8,I95+1/12,""),"") -> 6.6666667 | J96: =IF(I96<>"",J95+1/12,"") -> 71.666667 | K96: =IFERROR(VLOOKUP(J96,$B$3:$F$1060,3,TRUE),"") -> 0.018009833 | L96: =IF(I96<>"",1-K96,"") -> 0.98199017 | M96: =IF(I96<>"",M95*L95,"") -> 0.34854285 | N96: =IF(I96<>"",(1+$M$10)^-(1+I96),"") -> 0.51351429 | Q96: =IFERROR(IF(Q95+1/12<$J$8,Q95+1/12,""),"") -> 6.6666667 | R96: =IF(Q96<>"",R95*L95,"") -> 0.34854285 | S96: =IF(Q96<>"",(1+$M$10)^-(12*Q96),"") -> 0.00095428611 | T96: =IFERROR(S96*R96,"") -> 0.0003326096
B97: =B96+1/12 -> 19.75 | D97: =(B97-$B$88)*$D$88 -> 0.00050025 | E97: =E88-(9/12)*F88 -> 996001.74 | F97: =E97-E98 -> 55.388805 | G97: =1-D97 -> 0.99949975 | I97: =IFERROR(IF(I96+1/12<$J$8,I96+1/12,""),"") -> 6.75 | J97: =IF(I97<>"",J96+1/12,"") -> 71.75 | K97: =IFERROR(VLOOKUP(J97,$B$3:$F$1060,3,TRUE),"") -> 0.020582667 | L97: =IF(I97<>"",1-K97,"") -> 0.97941733 | M97: =IF(I97<>"",M96*L96,"") -> 0.34226565 | N97: =IF(I97<>"",(1+$M$10)^-(1+I97),"") -> 0.50980767 | Q97: =IFERROR(IF(Q96+1/12<$J$8,Q96+1/12,""),"") -> 6.75 | R97: =IF(Q97<>"",R96*L96,"") -> 0.34226565 | S97: =IF(Q97<>"",(1+$M$10)^-(12*Q97),"") -> 0.00087483185 | T97: =IFERROR(S97*R97,"") -> 0.00029942489
B98: =B97+1/12 -> 19.833333 | D98: =(B98-$B$88)*$D$88 -> 0.00055583333 | E98: =E88-(10/12)*F88 -> 995946.35 | F98: =E98-E99 -> 55.388805 | G98: =1-D98 -> 0.99944417 | I98: =IFERROR(IF(I97+1/12<$J$8,I97+1/12,""),"") -> 6.8333333 | J98: =IF(I98<>"",J97+1/12,"") -> 71.833333 | K98: =IFERROR(VLOOKUP(J98,$B$3:$F$1060,3,TRUE),"") -> 0.0231555 | L98: =IF(I98<>"",1-K98,"") -> 0.9768445 | M98: =IF(I98<>"",M97*L97,"") -> 0.33522091 | N98: =IF(I98<>"",(1+$M$10)^-(1+I98),"") -> 0.5061278 | Q98: =IFERROR(IF(Q97+1/12<$J$8,Q97+1/12,""),"") -> 6.8333333 | R98: =IF(Q98<>"",R97*L97,"") -> 0.33522091 | S98: =IF(Q98<>"",(1+$M$10)^-(12*Q98),"") -> 0.00080199298 | T98: =IFERROR(S98*R98,"") -> 0.00026884482
B99: =B98+1/12 -> 19.916667 | D99: =(B99-$B$88)*$D$88 -> 0.00061141667 | E99: =E88-(11/12)*F88 -> 995890.96 | F99: =E99-E100 -> 55.388805 | G99: =1-D99 -> 0.99938858 | I99: =IFERROR(IF(I98+1/12<$J$8,I98+1/12,""),"") -> 6.9166667 | J99: =IF(I99<>"",J98+1/12,"") -> 71.916667 | K99: =IFERROR(VLOOKUP(J99,$B$3:$F$1060,3,TRUE),"") -> 0.025728333 | L99: =IF(I99<>"",1-K99,"") -> 0.97427167 | M99: =IF(I99<>"",M98*L98,"") -> 0.3274587 | N99: =IF(I99<>"",(1+$M$10)^-(1+I99),"") -> 0.5024745 | Q99: =IFERROR(IF(Q98+1/12<$J$8,Q98+1/12,""),"") -> 6.9166667 | R99: =IF(Q99<>"",R98*L98,"") -> 0.3274587 | S99: =IF(Q99<>"",(1+$M$10)^-(12*Q99),"") -> 0.00073521871 | T99: =IFERROR(S99*R99,"") -> 0.00024075377
B100: 20 | C100: 0.718 | D100: =C100/1000 -> 0.000718 | E100: =E88-F88 -> 995835.58 | F100: =D100*E100 -> 715.00994 | G100: =1-D100 -> 0.999282 | I100: =IFERROR(IF(I99+1/12<$J$8,I99+1/12,""),"") -> 7 | J100: =IF(I100<>"",J99+1/12,"") -> 72 | K100: =IFERROR(VLOOKUP(J101,$B$3:$F$1060,3,TRUE),"") -> 0.03318 | L100: =IF(I100<>"",1-K100,"") -> 0.96682 | M100: =IF(I100<>"",M99*L99,"") -> 0.31903374 | N100: =IF(I100<>"",(1+$M$10)^-(1+I100),"") -> 0.49884757 | Q100: =IFERROR(IF(Q99+1/12<$J$8,Q99+1/12,""),"") -> 7 | R100: =IF(Q100<>"",R99*L99,"") -> 0.31903374 | S100: =IF(Q100<>"",(1+$M$10)^-(12*Q100),"") -> 0.00067400409 | T100: =IFERROR(S100*R100,"") -> 0.00021503004
B101: =B100+1/12 -> 20.083333 | D101: =(B101-$B$100)*$D$100 -> 5.9833333e-05 | E101: =E100-(1/12)*F100 -> 995775.99 | F101: =E101-E102 -> 59.584162 | G101: =1-D101 -> 0.99994017 | I101: =IFERROR(IF(I100+1/12<$J$8,I100+1/12,""),"") -> 7.0833333 | J101: =IF(I101<>"",J100+1/12,"") -> 72.083333 | K101: =IFERROR(VLOOKUP(J102,$B$3:$F$1060,3,TRUE),"") -> 0.002765 | L101: =IF(I101<>"",1-K101,"") -> 0.997235 | M101: =IF(I101<>"",M100*L100,"") -> 0.3084482 | N101: =IF(I101<>"",(1+$M$10)^-(1+I101),"") -> 0.49524682 | Q101: =IFERROR(IF(Q100+1/12<$J$8,Q100+1/12,""),"") -> 7.0833333 | R101: =IF(Q101<>"",R100*L100,"") -> 0.3084482 | S101: =IF(Q101<>"",(1+$M$10)^-(12*Q101),"") -> 0.00061788623 | T101: =IFERROR(S101*R101,"") -> 0.00019058589
B102: =B101+1/12 -> 20.166667 | D102: =(B102-$B$100)*$D$100 -> 0.00011966667 | E102: =E100-(2/12)*F100 -> 995716.41 | F102: =E102-E103 -> 59.584162 | G102: =1-D102 -> 0.99988033 | I102: =IFERROR(IF(I101+1/12<$J$8,I101+1/12,""),"") -> 7.1666667 | J102: =IF(I102<>"",J101+1/12,"") -> 72.166667 | K102: =IFERROR(VLOOKUP(J103,$B$3:$F$1060,3,TRUE),"") -> 0.00553 | L102: =IF(I102<>"",1-K102,"") -> 0.99447 | M102: =IF(I102<>"",M101*L101,"") -> 0.30759534 | N102: =IF(I102<>"",(1+$M$10)^-(1+I102),"") -> 0.49167205 | Q102: =IFERROR(IF(Q101+1/12<$J$8,Q101+1/12,""),"") -> 7.1666667 | R102: =IF(Q102<>"",R101*L101,"") -> 0.30759534 | S102: =IF(Q102<>"",(1+$M$10)^-(12*Q102),"") -> 0.00056644076 | T102: =IFERROR(S102*R102,"") -> 0.00017423454
...

Sheet Anual
K1: Seguro de Rentas Vitalicias | N1: Calculo de Renta Anual
G2: Moneda | H2: Pesos
B3: Edad | C3: CNSF 2000-I | D3: qx
B4: 12 | C4: 0.396 | D4: =C4/1000 -> 0.000396 | G4: Edad Contratación | H4: ='Prima Riesgo'!C6 -> 65 | J4: Valor Anualidad | K4: =Q12 -> 8.3988896 | M4: ¿Cuánto pagarás de prima única? | N4: ='Prima Riesgo'!I6 -> 1000000 | P4: ¿Cuánto quieres recibir de Renta Anual? | Q4: ='Prima Riesgo'!L8 -> 7500
B5: 13 | C5: 0.427 | D5: =C5/1000 -> 0.000427
B6: 14 | C6: 0.46 | D6: =C6/1000 -> 0.00046 | G6: Plazo del Seguro (w-x) | H6: =B92-H4 -> 35 | J6: Tasa interes técnico | K6: ='Prima Riesgo'!F8 -> 0.0947 | M6: Recibirás de Renta Anual: | N6: =N4/Q12 -> 119063.36 | P6: Debes pagar como Prima Única: | Q6: =Q4*Q12 -> 62991.672
B7: 15 | C7: 0.495 | D7: =C7/1000 -> 0.000495
B8: 16 | C8: 0.533 | D8: =C8/1000 -> 0.000533
B9: 17 | C9: 0.575 | D9: =C9/1000 -> 0.000575 | J9: =IF(K8>K4,"El plazo de pago de primas es incorrecto","")
B10: 18 | C10: 0.619 | D10: =C10/1000 -> 0.000619
B11: 19 | C11: 0.667 | D11: =C11/1000 -> 0.000667
B12: 20 | C12: 0.718 | D12: =C12/1000 -> 0.000718 | P12: suma flujo anualidad | Q12: =SUM(Q14:Q104) -> 8.3988896
B13: 21 | C13: 0.773 | D13: =C13/1000 -> 0.000773 | F13: t | G13: (x) | H13: qx+t | I13: px | J13: tpx | K13: V^t | N13: s | O13: spx | P13: V^s | Q13: Flujo Anualidad
B14: 22 | C14: 0.833 | D14: =C14/1000 -> 0.000833 | F14: 0 | G14: =H4 -> 65 | H14: =IFERROR(VLOOKUP(G14,$B$3:$D$92,3,FALSE),"") -> 0.01998 | I14: =IF(F14<>"",1-H14,"") -> 0.98002 | J14: =IF(F14<>"",1,"") -> 1 | K14: =IF(F14<>"",(1+$K$6)^-(1+F14),"") -> 0.91349228 | N14: 0 | O14: =IF(N14<>"",1,"") -> 1 | P14: =IF(N14<>"",(1+$K$6)^-(N14),"") -> 1 | Q14: =IFERROR(P14*O14,"") -> 1
B15: 23 | C15: 0.897 | D15: =C15/1000 -> 0.000897 | F15: =IFERROR(IF(F14+1<$H$6,F14+1,""),"") -> 1 | G15: =IF(F15<>"",G14+1,"") -> 66 | H15: =IFERROR(VLOOKUP(G15,$B$3:$D$92,3,FALSE),"") -> 0.02149 | I15: =IF(F15<>"",1-H15,"") -> 0.97851 | J15: =IF(F15<>"",J14*I14,"") -> 0.98002 | K15: =IF(F15<>"",(1+$K$6)^-(1+F15),"") -> 0.83446815 | N15: =IFERROR(IF(N14+1<$H$6,N14+1,""),"") -> 1 | O15: =IF(N15<>"",O14*I14,"") -> 0.98002 | P15: =IF(N15<>"",(1+$K$6)^-(N15),"") -> 0.91349228 | Q15: =IFERROR(P15*O15,"") -> 0.89524071
B16: 24 | C16: 0.966 | D16: =C16/1000 -> 0.000966 | F16: =IFERROR(IF(F15+1<$H$6,F15+1,""),"") -> 2 | G16: =IF(F16<>"",G15+1,"") -> 67 | H16: =IFERROR(VLOOKUP(G16,$B$3:$D$92,3,FALSE),"") -> 0.023111 | I16: =IF(F16<>"",1-H16,"") -> 0.976889 | J16: =IF(F16<>"",J15*I15,"") -> 0.95895937 | K16: =IF(F16<>"",(1+$K$6)^-(1+F16),"") -> 0.76228021 | N16: =IFERROR(IF(N15+1<$H$6,N15+1,""),"") -> 2 | O16: =IF(N16<>"",O15*I15,"") -> 0.95895937 | P16: =IF(N16<>"",(1+$K$6)^-(N16),"") -> 0.83446815 | Q16: =IFERROR(P16*O16,"") -> 0.80022105
B17: 25 | C17: 1.041 | D17: =C17/1000 -> 0.001041 | F17: =IFERROR(IF(F16+1<$H$6,F16+1,""),"") -> 3 | G17: =IF(F17<>"",G16+1,"") -> 68 | H17: =IFERROR(VLOOKUP(G17,$B$3:$D$92,3,FALSE),"") -> 0.024851 | I17: =IF(F17<>"",1-H17,"") -> 0.975149 | J17: =IF(F17<>"",J16*I16,"") -> 0.93679686 | K17: =IF(F17<>"",(1+$K$6)^-(1+F17),"") -> 0.69633709 | N17: =IFERROR(IF(N16+1<$H$6,N16+1,""),"") -> 3 | O17: =IF(N17<>"",O16*I16,"") -> 0.93679686 | P17: =IF(N17<>"",(1+$K$6)^-(N17),"") -> 0.76228021 | Q17: =IFERROR(P17*O17,"") -> 0.71410171
B18: 26 | C18: 1.121 | D18: =C18/1000 -> 0.001121 | F18: =IFERROR(IF(F17+1<$H$6,F17+1,""),"") -> 4 | G18: =IF(F18<>"",G17+1,"") -> 69 | H18: =IFERROR(VLOOKUP(G18,$B$3:$D$92,3,FALSE),"") -> 0.02672 | I18: =IF(F18<>"",1-H18,"") -> 0.97328 | J18: =IF(F18<>"",J17*I17,"") -> 0.91351652 | K18: =IF(F18<>"",(1+$K$6)^-(1+F18),"") -> 0.63609856 | N18: =IFERROR(IF(N17+1<$H$6,N17+1,""),"") -> 4 | O18: =IF(N18<>"",O17*I17,"") -> 0.91351652 | P18: =IF(N18<>"",(1+$K$6)^-(N18),"") -> 0.69633709 | Q18: =IFERROR(P18*O18,"") -> 0.63611544
B19: 27 | C19: 1.207 | D19: =C19/1000 -> 0.001207 | F19: =IFERROR(IF(F18+1<$H$6,F18+1,""),"") -> 5 | G19: =IF(F19<>"",G18+1,"") -> 70 | H19: =IFERROR(VLOOKUP(G19,$B$3:$D$92,3,FALSE),"") -> 0.028724 | I19: =IF(F19<>"",1-H19,"") -> 0.971276 | J19: =IF(F19<>"",J18*I18,"") -> 0.88910736 | K19: =IF(F19<>"",(1+$K$6)^-(1+F19),"") -> 0.58107112 | N19: =IFERROR(IF(N18+1<$H$6,N18+1,""),"") -> 5 | O19: =IF(N19<>"",O18*I18,"") -> 0.88910736 | P19: =IF(N19<>"",(1+$K$6)^-(N19),"") -> 0.63609856 | Q19: =IFERROR(P19*O19,"") -> 0.56555991
B20: 28 | C20: 1.3 | D20: =C20/1000 -> 0.0013 | F20: =IFERROR(IF(F19+1<$H$6,F19+1,""),"") -> 6 | G20: =IF(F20<>"",G19+1,"") -> 71 | H20: =IFERROR(VLOOKUP(G20,$B$3:$D$92,3,FALSE),"") -> 0.030874 | I20: =IF(F20<>"",1-H20,"") -> 0.969126 | J20: =IF(F20<>"",J19*I19,"") -> 0.86356864 | K20: =IF(F20<>"",(1+$K$6)^-(1+F20),"") -> 0.53080398 | N20: =IFERROR(IF(N19+1<$H$6,N19+1,""),"") -> 6 | O20: =IF(N20<>"",O19*I19,"") -> 0.86356864 | P20: =IF(N20<>"",(1+$K$6)^-(N20),"") -> 0.58107112 | Q20: =IFERROR(P20*O20,"") -> 0.5017948
B21: 29 | C21: 1.4 | D21: =C21/1000 -> 0.0014 | F21: =IFERROR(IF(F20+1<$H$6,F20+1,""),"") -> 7 | G21: =IF(F21<>"",G20+1,"") -> 72 | H21: =IFERROR(VLOOKUP(G21,$B$3:$D$92,3,FALSE),"") -> 0.03318 | I21: =IF(F21<>"",1-H21,"") -> 0.96682 | J21: =IF(F21<>"",J20*I20,"") -> 0.83690682 | K21: =IF(F21<>"",(1+$K$6)^-(1+F21),"") -> 0.48488534 | N21: =IFERROR(IF(N20+1<$H$6,N20+1,""),"") -> 7 | O21: =IF(N21<>"",O20*I20,"") -> 0.83690682 | P21: =IF(N21<>"",(1+$K$6)^-(N21),"") -> 0.53080398 | Q21: =IFERROR(P21*O21,"") -> 0.44423347
B22: 30 | C22: 1.508 | D22: =C22/1000 -> 0.001508 | F22: =IFERROR(IF(F21+1<$H$6,F21+1,""),"") -> 8 | G22: =IF(F22<>"",G21+1,"") -> 73 | H22: =IFERROR(VLOOKUP(G22,$B$3:$D$92,3,FALSE),"") -> 0.035651 | I22: =IF(F22<>"",1-H22,"") -> 0.964349 | J22: =IF(F22<>"",J21*I21,"") -> 0.80913825 | K22: =IF(F22<>"",(1+$K$6)^-(1+F22),"") -> 0.44293902 | N22: =IFERROR(IF(N21+1<$H$6,N21+1,""),"") -> 8 | O22: =IF(N22<>"",O21*I21,"") -> 0.80913825 | P22: =IF(N22<>"",(1+$K$6)^-(N22),"") -> 0.48488534 | Q22: =IFERROR(P22*O22,"") -> 0.39233928
B23: 31 | C23: 1.624 | D23: =C23/1000 -> 0.001624 | F23: =IFERROR(IF(F22+1<$H$6,F22+1,""),"") -> 9 | G23: =IF(F23<>"",G22+1,"") -> 74 | H23: =IFERROR(VLOOKUP(G23,$B$3:$D$92,3,FALSE),"") -> 0.0383 | I23: =IF(F23<>"",1-H23,"") -> 0.9617 | J23: =IF(F23<>"",J22*I22,"") -> 0.78029167 | K23: =IF(F23<>"",(1+$K$6)^-(1+F23),"") -> 0.40462137 | N23: =IFERROR(IF(N22+1<$H$6,N22+1,""),"") -> 9 | O23: =IF(N23<>"",O22*I22,"") -> 0.78029167 | P23: =IF(N23<>"",(1+$K$6)^-(N23),"") -> 0.44293902 | Q23: =IFERROR(P23*O23,"") -> 0.34562162
B24: 32 | C24: 1.749 | D24: =C24/1000 -> 0.001749 | F24: =IFERROR(IF(F23+1<$H$6,F23+1,""),"") -> 10 | G24: =IF(F24<>"",G23+1,"") -> 75 | H24: =IFERROR(VLOOKUP(G24,$B$3:$D$92,3,FALSE),"") -> 0.041136 | I24: =IF(F24<>"",1-H24,"") -> 0.958864 | J24: =IF(F24<>"",J23*I23,"") -> 0.75040649 | K24: =IF(F24<>"",(1+$K$6)^-(1+F24),"") -> 0.3696185 | N24: =IFERROR(IF(N23+1<$H$6,N23+1,""),"") -> 10 | O24: =IF(N24<>"",O23*I23,"") -> 0.75040649 | P24: =IF(N24<>"",(1+$K$6)^-(N24),"") -> 0.40462137 | Q24: =IFERROR(P24*O24,"") -> 0.30363051
B25: 33 | C25: 1.884 | D25: =C25/1000 -> 0.001884 | F25: =IFERROR(IF(F24+1<$H$6,F24+1,""),"") -> 11 | G25: =IF(F25<>"",G24+1,"") -> 76 | H25: =IFERROR(VLOOKUP(G25,$B$3:$D$92,3,FALSE),"") -> 0.044174 | I25: =IF(F25<>"",1-H25,"") -> 0.955826 | J25: =IF(F25<>"",J24*I24,"") -> 0.71953777 | K25: =IF(F25<>"",(1+$K$6)^-(1+F25),"") -> 0.33764365 | N25: =IFERROR(IF(N24+1<$H$6,N24+1,""),"") -> 11 | O25: =IF(N25<>"",O24*I24,"") -> 0.71953777 | P25: =IF(N25<>"",(1+$K$6)^-(N25),"") -> 0.3696185 | Q25: =IFERROR(P25*O25,"") -> 0.26595447
B26: 34 | C26: 2.029 | D26: =C26/1000 -> 0.002029 | F26: =IFERROR(IF(F25+1<$H$6,F25+1,""),"") -> 12 | G26: =IF(F26<>"",G25+1,"") -> 77 | H26: =IFERROR(VLOOKUP(G26,$B$3:$D$92,3,FALSE),"") -> 0.047424 | I26: =IF(F26<>"",1-H26,"") -> 0.952576 | J26: =IF(F26<>"",J25*I25,"") -> 0.68775291 | K26: =IF(F26<>"",(1+$K$6)^-(1+F26),"") -> 0.30843487 | N26: =IFERROR(IF(N25+1<$H$6,N25+1,""),"") -> 12 | O26: =IF(N26<>"",O25*I25,"") -> 0.68775291 | P26: =IF(N26<>"",(1+$K$6)^-(N26),"") -> 0.33764365 | Q26: =IFERROR(P26*O26,"") -> 0.2322154
... B92: 100 | C92: 1000 | D92: =C92/1000 -> 1 | F92: =IFERROR(IF(F91+1<$H$6,F91+1,""),"") | G92: =IF(F92<>"",G91+1,"") | H92: =IFERROR(VLOOKUP(G92,$B$3:$D$92,3,FALSE),"") | I92: =IF(F92<>"",1-H92,"") | J92: =IF(F92<>"",J91*I91,"") | K92: =IF(F92<>"",(1+$K$6)^-(1+F92),"") | N92: =IFERROR(IF(N91+1<$H$6,N91+1,""),"") | O92: =IF(N92<>"",O91*I91,"") | P92: =IF(N92<>"",(1+$K$6)^-(N92),"") | Q92: =IFERROR(P92*O92,"")
F93: =IFERROR(IF(F92+1<$H$6,F92+1,""),"") | G93: =IF(F93<>"",G92+1,"") | H93: =IFERROR(VLOOKUP(G93,$B$3:$D$92,3,FALSE),"") | I93: =IF(F93<>"",1-H93,"") | J93: =IF(F93<>"",J92*I92,"") | K93: =IF(F93<>"",(1+$K$6)^-(1+F93),"") | N93: =IFERROR(IF(N92+1<$H$6,N92+1,""),"") | O93: =IF(N93<>"",O92*I92,"") | P93: =IF(N93<>"",(1+$K$6)^-(N93),"") | Q93: =IFERROR(P93*O93,"")
F94: =IFERROR(IF(F93+1<$H$6,F93+1,""),"") | G94: =IF(F94<>"",G93+1,"") | H94: =IFERROR(VLOOKUP(G94,$B$3:$D$92,3,FALSE),"") | I94: =IF(F94<>"",1-H94,"") | J94: =IF(F94<>"",J93*I93,"") | K94: =IF(F94<>"",(1+$K$6)^-(1+F94),"") | N94: =IFERROR(IF(N93+1<$H$6,N93+1,""),"") | O94: =IF(N94<>"",O93*I93,"") | P94: =IF(N94<>"",(1+$K$6)^-(N94),"") | Q94: =IFERROR(P94*O94,"")
F95: =IFERROR(IF(F94+1<$H$6,F94+1,""),"") | G95: =IF(F95<>"",G94+1,"") | H95: =IFERROR(VLOOKUP(G95,$B$3:$D$92,3,FALSE),"") | I95: =IF(F95<>"",1-H95,"") | J95: =IF(F95<>"",J94*I94,"") | K95: =IF(F95<>"",(1+$K$6)^-(1+F95),"") | N95: =IFERROR(IF(N94+1<$H$6,N94+1,""),"") | O95: =IF(N95<>"",O94*I94,"") | P95: =IF(N95<>"",(1+$K$6)^-(N95),"") | Q95: =IFERROR(P95*O95,"")
F96: =IFERROR(IF(F95+1<$H$6,F95+1,""),"") | G96: =IF(F96<>"",G95+1,"") | H96: =IFERROR(VLOOKUP(G96,$B$3:$D$92,3,FALSE),"") | I96: =IF(F96<>"",1-H96,"") | J96: =IF(F96<>"",J95*I95,"") | K96: =IF(F96<>"",(1+$K$6)^-(1+F96),"") | N96: =IFERROR(IF(N95+1<$H$6,N95+1,""),"") | O96: =IF(N96<>"",O95*I95,"") | P96: =IF(N96<>"",(1+$K$6)^-(N96),"") | Q96: =IFERROR(P96*O96,"")
F97: =IFERROR(IF(F96+1<$H$6,F96+1,""),"") | G97: =IF(F97<>"",G96+1,"") | H97: =IFERROR(VLOOKUP(G97,$B$3:$D$92,3,FALSE),"") | I97: =IF(F97<>"",1-H97,"") | J97: =IF(F97<>"",J96*I96,"") | K97: =IF(F97<>"",(1+$K$6)^-(1+F97),"") | N97: =IFERROR(IF(N96+1<$H$6,N96+1,""),"") | O97: =IF(N97<>"",O96*I96,"") | P97: =IF(N97<>"",(1+$K$6)^-(N97),"") | Q97: =IFERROR(P97*O97,"")
F98: =IFERROR(IF(F97+1<$H$6,F97+1,""),"") | G98: =IF(F98<>"",G97+1,"") | H98: =IFERROR(VLOOKUP(G98,$B$3:$D$92,3,FALSE),"") | I98: =IF(F98<>"",1-H98,"") | J98: =IF(F98<>"",J97*I97,"") | K98: =IF(F98<>"",(1+$K$6)^-(1+F98),"") | N98: =IFERROR(IF(N97+1<$H$6,N97+1,""),"") | O98: =IF(N98<>"",O97*I97,"") | P98: =IF(N98<>"",(1+$K$6)^-(N98),"") | Q98: =IFERROR(P98*O98,"")
F99: =IFERROR(IF(F98+1<$H$6,F98+1,""),"") | G99: =IF(F99<>"",G98+1,"") | H99: =IFERROR(VLOOKUP(G99,$B$3:$D$92,3,FALSE),"") | I99: =IF(F99<>"",1-H99,"") | J99: =IF(F99<>"",J98*I98,"") | K99: =IF(F99<>"",(1+$K$6)^-(1+F99),"") | N99: =IFERROR(IF(N98+1<$H$6,N98+1,""),"") | O99: =IF(N99<>"",O98*I98,"") | P99: =IF(N99<>"",(1+$K$6)^-(N99),"") | Q99: =IFERROR(P99*O99,"")
F100: =IFERROR(IF(F99+1<$H$6,F99+1,""),"") | G100: =IF(F100<>"",G99+1,"") | H100: =IFERROR(VLOOKUP(G100,$B$3:$D$92,3,FALSE),"") | I100: =IF(F100<>"",1-H100,"") | J100: =IF(F100<>"",J99*I99,"") | K100: =IF(F100<>"",(1+$K$6)^-(1+F100),"") | N100: =IFERROR(IF(N99+1<$H$6,N99+1,""),"") | O100: =IF(N100<>"",O99*I99,"") | P100: =IF(N100<>"",(1+$K$6)^-(N100),"") | Q100: =IFERROR(P100*O100,"")
F101: =IFERROR(IF(F100+1<$H$6,F100+1,""),"") | G101: =IF(F101<>"",G100+1,"") | H101: =IFERROR(VLOOKUP(G101,$B$3:$D$92,3,FALSE),"") | I101: =IF(F101<>"",1-H101,"") | J101: =IF(F101<>"",J100*I100,"") | K101: =IF(F101<>"",(1+$K$6)^-(1+F101),"") | N101: =IFERROR(IF(N100+1<$H$6,N100+1,""),"") | O101: =IF(N101<>"",O100*I100,"") | P101: =IF(N101<>"",(1+$K$6)^-(N101),"") | Q101: =IFERROR(P101*O101,"")
F102: =IFERROR(IF(F101+1<$H$6,F101+1,""),"") | G102: =IF(F102<>"",G101+1,"") | H102: =IFERROR(VLOOKUP(G102,$B$3:$D$92,3,FALSE),"") | I102: =IF(F102<>"",1-H102,"") | J102: =IF(F102<>"",J101*I101,"") | K102: =IF(F102<>"",(1+$K$6)^-(1+F102),"") | N102: =IFERROR(IF(N101+1<$H$6,N101+1,""),"") | O102: =IF(N102<>"",O101*I101,"") | P102: =IF(N102<>"",(1+$K$6)^-(N102),"") | Q102: =IFERROR(P102*O102,"")
F103: =IFERROR(IF(F102+1<$H$6,F102+1,""),"") | G103: =IF(F103<>"",G102+1,"") | H103: =IFERROR(VLOOKUP(G103,$B$3:$D$92,3,FALSE),"") | I103: =IF(F103<>"",1-H103,"") | J103: =IF(F103<>"",J102*I102,"") | K103: =IF(F103<>"",(1+$K$6)^-(1+F103),"") | N103: =IFERROR(IF(N102+1<$H$6,N102+1,""),"") | O103: =IF(N103<>"",O102*I102,"") | P103: =IF(N103<>"",(1+$K$6)^-(N103),"") | Q103: =IFERROR(P103*O103,"")
F104: =IFERROR(IF(F103+1<$H$6,F103+1,""),"") | G104: =IF(F104<>"",G103+1,"") | H104: =IFERROR(VLOOKUP(G104,$B$3:$D$92,3,FALSE),"") | I104: =IF(F104<>"",1-H104,"") | J104: =IF(F104<>"",J103*I103,"") | K104: =IF(F104<>"",(1+$K$6)^-(1+F104),"") | N104: =IFERROR(IF(N103+1<$H$6,N103+1,""),"") | O104: =IF(N104<>"",O103*I103,"") | P104: =IF(N104<>"",(1+$K$6)^-(N104),"") | Q104: =IFERROR(P104*O104,"")
